Proyecto/Lab_08/mipsmulti.v
//-------------------------------------------------------
// mipsmulti.v
// Multicycle MIPS processor
//------------------------------------------------

module controller(input         clk, reset,
                  input   [5:0] op, funct,
                  input         zero,
                  output        pcen, memwrite, irwrite, regwrite,
                  output        alusrca, iord, memtoreg, regdst,
                  output  [1:0] alusrcb, pcsrc,
                  output  [2:0] alucontrol);

  wire [1:0] aluop;
  wire       branch, pcwrite;

  // Main Decoder and ALU Decoder subunits.
  maindec md(clk, reset, op,
             pcwrite, memwrite, irwrite, regwrite,
             alusrca, branch, iord, memtoreg, regdst, 
             alusrcb, pcsrc, aluop);
  aludec  ad(funct, aluop, alucontrol);
  // Implementacion del pcen a partir de lo observado
  // en el schematic
  assign pcen = (zero & branch) | pcwrite;
 
endmodule

module maindec(input         clk, reset, 
               input   [5:0] op, 
               output        pcwrite, memwrite, 
                    		 irwrite, regwrite,
               output        alusrca, branch, 
                             iord, memtoreg, regdst,
               output  [1:0] alusrcb, pcsrc,
               output  [1:0] aluop);

  parameter   FETCH   = 4'b0000;  // State 0
  parameter   DECODE  = 4'b0001;  // State 1
  parameter   MEMADR  = 4'b0010;	// State 2
  parameter   MEMRD   = 4'b0011;	// State 3
  parameter   MEMWB   = 4'b0100;	// State 4
  parameter   MEMWR   = 4'b0101;	// State 5
  parameter   RTYPEEX = 4'b0110;	// State 6
  parameter   RTYPEWB = 4'b0111;	// State 7
  parameter   BEQEX   = 4'b1000;	// State 8
  parameter   ADDIEX  = 4'b1001;	// State 9
  parameter   ADDIWB  = 4'b1010;	// state 10
  parameter   JEX     = 4'b1011;	// State 11

  parameter   LW      = 6'b100011;	// Opcode for lw
  parameter   SW      = 6'b101011;	// Opcode for sw
  parameter   RTYPE   = 6'b000000;	// Opcode for R-type
  parameter   BEQ     = 6'b000100;	// Opcode for beq
  parameter   ADDI    = 6'b001000;	// Opcode for addi
  parameter   J       = 6'b000010;	// Opcode for j

  reg [3:0]  state, nextstate;
  reg [14:0] controls;

  // state register
  always @(posedge clk or posedge reset)			
    if(reset) state <= FETCH;
    else state <= nextstate;

  // next state logic
  always @(*)
    case(state)
      FETCH:   nextstate <= DECODE;
      DECODE:  case(op)
                 LW:      nextstate <= MEMADR;
                 SW:      nextstate <= MEMADR;
                 RTYPE:   nextstate <= RTYPEEX;
                 BEQ:     nextstate <= BEQEX;
                 ADDI:    nextstate <= ADDIEX;
                 J:       nextstate <= JEX;
                 default: nextstate <= FETCH; // 4'bx should never happen
               endcase
      MEMADR: case(op)
				LW:	nextstate <= MEMRD;
				SW: nextstate <= MEMWR;
				default: nextstate <= FETCH; // should never happen
			  endcase
      MEMRD: nextstate <= MEMWB;
      MEMWB: nextstate <= FETCH;
      MEMWR: nextstate <= FETCH;
      RTYPEEX: nextstate <= RTYPEWB;
      RTYPEWB: nextstate <= FETCH;
      BEQEX:   nextstate <= FETCH; 
      ADDIEX:  nextstate <= ADDIWB;
      ADDIWB:  nextstate <= FETCH;
      JEX:     nextstate <= FETCH;
      default: nextstate <= FETCH; // should never happen
    endcase

  // output logic
  assign {pcwrite, memwrite, irwrite, regwrite, 
          alusrca, branch, iord, memtoreg, regdst,
          alusrcb, pcsrc, aluop} = controls;

  //Logica ouput para cada estado
  always @(*)
    case(state)
      FETCH:   controls <= 15'h5010; //S0
      DECODE:  controls <= 15'h0030; //S1
	    MEMADR:  controls <= 15'h0420; //S2
	    MEMRD:   controls <= 15'h0100; //S3
      MEMWB:   controls <= 15'h0880; //S4
  	  MEMWR:   controls <= 15'h2100; //S5
	    RTYPEEX: controls <= 15'h0402; //S6
	    RTYPEWB: controls <= 15'h0840; //S7
      BEQEX:   controls <= 15'h0605; //S8
	    ADDIEX:  controls <= 15'h0420; //S9
	    ADDIWB:  controls <= 15'h0800; //S10
	    JEX:     controls <= 15'h4008; //S11
      default: controls <= 15'hxxxx; // should never happen
    endcase
endmodule

//Implementacion del ALUDEC
module aludec(input   [5:0] funct,
              input   [1:0] aluop,
              output reg [2:0] alucontrol);
	always @(*)
		case(aluop)
		 2'b00: alucontrol <= 3'b010;
		 2'b01: alucontrol <= 3'b110;
		 default: case(funct)
		 	6'b100000: alucontrol <= 3'b010; //add
			6'b100010: alucontrol <= 3'b110; //sub
			6'b100100: alucontrol <= 3'b000; //and
			6'b100101: alucontrol <= 3'b001; //or
			6'b101010: alucontrol <= 3'b111; //slt
			default:   alucontrol <= 3'bxxx; //???
          endcase
		endcase
endmodule

Proyecto/Lab_08/multitest.v
//------------------------------------------------
// Testbench for MIPS processor
module testbench();

  reg        clk, reset, zero;
  reg [5:0] opcode, funct;
  
  wire pcen, memwrite, irwrite, regwrite,
  		alusrca, iord, memtoreg, regdst;
  wire [1:0] alusrcb, pcsrc;
  wire [2:0] alucontrol;

  // instantiate device to be tested
  controller cont(clk, reset, opcode, funct, zero, 
            pcen, memwrite, irwrite, regwrite,
  				  alusrca, iord, memtoreg, regdst, alusrcb, pcsrc, 
            alucontrol);
  
  // initialize test
  initial
    begin
      reset <= 1; # 10; reset <= 0;
    end

  // generate clock to sequence tests
  always
    begin
      clk <= 1; # 5; clk <= 0; # 5;
    end

  initial begin
        opcode = 6'b000000; funct = 6'b100000; zero = 0; //add - 4 cycles
  	#40 opcode = 6'b000000; funct = 6'b100010; zero = 0; //sub - 4 cycles
  	#40 opcode = 6'b000000; funct = 6'b100100; zero = 0; //and - 4 cycles
  	#40 opcode = 6'b000000; funct = 6'b100101; zero = 0; //or  - 4 cycles
  	#40 opcode = 6'b000000; funct = 6'b101010; zero = 0; //slt - 4 cycles
  	#40	opcode = 6'b100011; funct = 6'bx; zero = 0; //lw - 5 cycles
  	#50 opcode = 6'b101011; funct = 6'bx; zero = 0; //sw - 4 cycles
  	#40 opcode = 6'b000100; funct = 6'bx; zero = 0; //beq - 3 cycles
  	#30 opcode = 6'b000100; funct = 6'bx; zero = 1; //beq - 3 cycles
  	#30 opcode = 6'b001000; funct = 6'bx; zero = 0; //addi - 4 cycles
  	#40 opcode = 6'b000010; funct = 6'bx; zero = 0; //j - 3 cycles
    #30 $finish;
  	
  end
  	
    	initial begin
		$dumpfile("lab08.vcd");	
		$dumpvars;
	end	

endmodule

Proyecto/Lab_08/lab08.vcd
$date
	Thu Jul 23 19:50:36 2020
$end
$version
	Icarus Verilog
$end
$timescale
	1s
$end
$scope module testbench $end
$var wire 1 ! regwrite $end
$var wire 1 " regdst $end
$var wire 2 # pcsrc [1:0] $end
$var wire 1 $ pcen $end
$var wire 1 % memwrite $end
$var wire 1 & memtoreg $end
$var wire 1 ' irwrite $end
$var wire 1 ( iord $end
$var wire 2 ) alusrcb [1:0] $end
$var wire 1 * alusrca $end
$var wire 3 + alucontrol [2:0] $end
$var reg 1 , clk $end
$var reg 6 - funct [5:0] $end
$var reg 6 . opcode [5:0] $end
$var reg 1 / reset $end
$var reg 1 0 zero $end
$scope module cont $end
$var wire 1 , clk $end
$var wire 6 1 funct [5:0] $end
$var wire 6 2 op [5:0] $end
$var wire 1 $ pcen $end
$var wire 1 / reset $end
$var wire 1 0 zero $end
$var wire 1 ! regwrite $end
$var wire 1 " regdst $end
$var wire 1 3 pcwrite $end
$var wire 2 4 pcsrc [1:0] $end
$var wire 1 % memwrite $end
$var wire 1 & memtoreg $end
$var wire 1 ' irwrite $end
$var wire 1 ( iord $end
$var wire 1 5 branch $end
$var wire 2 6 alusrcb [1:0] $end
$var wire 1 * alusrca $end
$var wire 2 7 aluop [1:0] $end
$var wire 3 8 alucontrol [2:0] $end
$scope module ad $end
$var wire 6 9 funct [5:0] $end
$var wire 2 : aluop [1:0] $end
$var reg 3 ; alucontrol [2:0] $end
$upscope $end
$scope module md $end
$var wire 1 , clk $end
$var wire 6 < op [5:0] $end
$var wire 1 / reset $end
$var wire 1 ! regwrite $end
$var wire 1 " regdst $end
$var wire 1 3 pcwrite $end
$var wire 2 = pcsrc [1:0] $end
$var wire 1 % memwrite $end
$var wire 1 & memtoreg $end
$var wire 1 ' irwrite $end
$var wire 1 ( iord $end
$var wire 1 5 branch $end
$var wire 2 > alusrcb [1:0] $end
$var wire 1 * alusrca $end
$var wire 2 ? aluop [1:0] $end
$var reg 15 @ controls [14:0] $end
$var reg 4 A nextstate [3:0] $end
$var reg 4 B state [3:0] $end
$upscope $end
$upscope $end
$upscope $end
$enddefinitions $end
#0
$dumpvars
b0 B
b1 A
b101000000010000 @
b0 ?
b1 >
b0 =
b0 <
b10 ;
b0 :
b100000 9
b10 8
b0 7
b1 6
05
b0 4
13
b0 2
b100000 1
00
1/
b0 .
b100000 -
1,
b10 +
0*
b1 )
0(
1'
0&
0%
1$
b0 #
0"
0!
$end
#5
0,
#10
0$
03
0'
b11 )
b11 6
b11 >
b110000 @
b110 A
b1 B
1,
0/
#15
0,
#20
1*
b0 )
b0 6
b0 >
b10 7
b10 :
b10 ?
b10000000010 @
b111 A
b110 B
1,
#25
0,
#30
1!
0*
1"
b0 7
b0 :
b0 ?
b100001000000 @
b0 A
b111 B
1,
#35
0,
#40
1$
13
1'
0!
0"
b1 )
b1 6
b1 >
b101000000010000 @
b1 A
b0 B
1,
b100010 -
b100010 1
b100010 9
#45
0,
#50
0$
03
0'
b11 )
b11 6
b11 >
b110000 @
b110 A
b1 B
1,
#55
0,
#60
b110 +
b110 8
b110 ;
1*
b0 )
b0 6
b0 >
b10 7
b10 :
b10 ?
b10000000010 @
b111 A
b110 B
1,
#65
0,
#70
b10 +
b10 8
b10 ;
1!
0*
1"
b0 7
b0 :
b0 ?
b100001000000 @
b0 A
b111 B
1,
#75
0,
#80
1$
13
1'
0!
0"
b1 )
b1 6
b1 >
b101000000010000 @
b1 A
b0 B
1,
b100100 -
b100100 1
b100100 9
#85
0,
#90
0$
03
0'
b11 )
b11 6
b11 >
b110000 @
b110 A
b1 B
1,
#95
0,
#100
b0 +
b0 8
b0 ;
1*
b0 )
b0 6
b0 >
b10 7
b10 :
b10 ?
b10000000010 @
b111 A
b110 B
1,
#105
0,
#110
b10 +
b10 8
b10 ;
1!
0*
1"
b0 7
b0 :
b0 ?
b100001000000 @
b0 A
b111 B
1,
#115
0,
#120
1$
13
1'
0!
0"
b1 )
b1 6
b1 >
b101000000010000 @
b1 A
b0 B
1,
b100101 -
b100101 1
b100101 9
#125
0,
#130
0$
03
0'
b11 )
b11 6
b11 >
b110000 @
b110 A
b1 B
1,
#135
0,
#140
b1 +
b1 8
b1 ;
1*
b0 )
b0 6
b0 >
b10 7
b10 :
b10 ?
b10000000010 @
b111 A
b110 B
1,
#145
0,
#150
b10 +
b10 8
b10 ;
1!
0*
1"
b0 7
b0 :
b0 ?
b100001000000 @
b0 A
b111 B
1,
#155
0,
#160
1$
13
1'
0!
0"
b1 )
b1 6
b1 >
b101000000010000 @
b1 A
b0 B
1,
b101010 -
b101010 1
b101010 9
#165
0,
#170
0$
03
0'
b11 )
b11 6
b11 >
b110000 @
b110 A
b1 B
1,
#175
0,
#180
b111 +
b111 8
b111 ;
1*
b0 )
b0 6
b0 >
b10 7
b10 :
b10 ?
b10000000010 @
b111 A
b110 B
1,
#185
0,
#190
b10 +
b10 8
b10 ;
1!
0*
1"
b0 7
b0 :
b0 ?
b100001000000 @
b0 A
b111 B
1,
#195
0,
#200
1$
13
1'
0!
0"
b1 )
b1 6
b1 >
b101000000010000 @
b1 A
b0 B
1,
bx -
bx 1
bx 9
b100011 .
b100011 2
b100011 <
#205
0,
#210
0$
03
0'
b11 )
b11 6
b11 >
b110000 @
b10 A
b1 B
1,
#215
0,
#220
1*
b10 )
b10 6
b10 >
b10000100000 @
b11 A
b10 B
1,
#225
0,
#230
0*
1(
b0 )
b0 6
b0 >
b100000000 @
b100 A
b11 B
1,
#235
0,
#240
1!
0(
1&
b100010000000 @
b0 A
b100 B
1,
#245
0,
#250
1$
13
1'
0!
0&
b1 )
b1 6
b1 >
b101000000010000 @
b1 A
b0 B
1,
b101011 .
b101011 2
b101011 <
#255
0,
#260
0$
03
0'
b11 )
b11 6
b11 >
b110000 @
b10 A
b1 B
1,
#265
0,
#270
1*
b10 )
b10 6
b10 >
b10000100000 @
b101 A
b10 B
1,
#275
0,
#280
1%
0*
1(
b0 )
b0 6
b0 >
b10000100000000 @
b0 A
b101 B
1,
#285
0,
#290
1$
13
0%
1'
0(
b1 )
b1 6
b1 >
b101000000010000 @
b1 A
b0 B
1,
b100 .
b100 2
b100 <
#295
0,
#300
0$
03
0'
b11 )
b11 6
b11 >
b110000 @
b1000 A
b1 B
1,
#305
0,
#310
b110 +
b110 8
b110 ;
1*
15
b0 )
b0 6
b0 >
b1 #
b1 4
b1 =
b1 7
b1 :
b1 ?
b11000000101 @
b0 A
b1000 B
1,
#315
0,
#320
b10 +
b10 8
b10 ;
13
1'
0*
05
b1 )
b1 6
b1 >
b0 #
b0 4
b0 =
b0 7
b0 :
b0 ?
b101000000010000 @
b1 A
b0 B
1,
1$
10
#325
0,
#330
0$
03
0'
b11 )
b11 6
b11 >
b110000 @
b1000 A
b1 B
1,
#335
0,
#340
b110 +
b110 8
b110 ;
1$
1*
15
b0 )
b0 6
b0 >
b1 #
b1 4
b1 =
b1 7
b1 :
b1 ?
b11000000101 @
b0 A
b1000 B
1,
#345
0,
#350
b10 +
b10 8
b10 ;
13
1'
0*
05
b1 )
b1 6
b1 >
b0 #
b0 4
b0 =
b0 7
b0 :
b0 ?
b101000000010000 @
b1 A
b0 B
1,
1$
00
b1000 .
b1000 2
b1000 <
#355
0,
#360
0$
03
0'
b11 )
b11 6
b11 >
b110000 @
b1001 A
b1 B
1,
#365
0,
#370
1*
b10 )
b10 6
b10 >
b10000100000 @
b1010 A
b1001 B
1,
#375
0,
#380
1!
0*
b0 )
b0 6
b0 >
b100000000000 @
b0 A
b1010 B
1,
#385
0,
#390
1$
13
1'
0!
b1 )
b1 6
b1 >
b101000000010000 @
b1 A
b0 B
1,
b10 .
b10 2
b10 <
#395
0,
#400
0$
03
0'
b11 )
b11 6
b11 >
b110000 @
b1011 A
b1 B
1,
#405
0,
#410
1$
13
b0 )
b0 6
b0 >
b10 #
b10 4
b10 =
b100000000001000 @
b0 A
b1011 B
1,
#415
0,
#420
1'
b1 )
b1 6
b1 >
b0 #
b0 4
b0 =
b101000000010000 @
b1 A
b0 B
1,
