Lab_04/seven.v
module seven (clk, reset, x1, x2, x3, state, z1, z2, z3);
	input clk, reset, x1, x2, x3;
	output z1, z2, z3;
	
	output reg [2:0] state;
	reg [2:0] nextstate;


	parameter a = 3'b000;
	parameter b = 3'b001;
	parameter c = 3'b101;
	parameter d = 3'b010;
	parameter e = 3'b100;
	parameter f = 3'b110;
	parameter g = 3'b111;

	always @ (posedge clk, posedge reset)
		if (reset) 
			state <= a;
		else 
			state <= nextstate;
	always @ (*)
		case (state)
			a:	if(x1)
					nextstate = b;
				else if (~x1)
					nextstate = c;
			b: 	if(x2)
					nextstate = d;
				else if(~x2)
					nextstate = a;	
			c:	if(x2 & x3)
					nextstate = e;
				else if(x2 & ~x3)
					nextstate = a;
				else if(~x2 & x3)
					nextstate = f;
				else if(~x2 & ~x3)
					nextstate = g;
			d:	nextstate = a;
			e:	nextstate = a;
			f:	nextstate = a;
			g:	nextstate = a;
			default:	nextstate = a;
		endcase

	assign z1 = (state==d);
	assign z2 = (state==e);
	assign z3 = (state==g);
endmodule

Lab_04/seven_tb.v
`timescale 1ns/1ns
module seven_tb;
	reg clk, reset, x1, x2, x3;
	wire [2:0] state;
	wire z1, z2, z3;
	seven g(clk, reset, x1, x2, x3, state, z1, z2, z3);
	initial begin
		$display("time\tclk\treset\tx1\tx2\tx3\tstate\tz1\tz2\tz3");
		clk <= 1;
		reset <= 0;
		x1 <= 0;
		x2 <= 0;
		x3 <= 0;



		#30 $finish;
	end
	initial begin
		$monitor("%2d\t%b\t%b\t%b\t%b\t%b\t%b\t%b\t%b\t%b", $time, clk, reset, x1, x2, x3, state, z1, z2, z3);
	end
	
		
	always
	#1 clk = ~clk;
	
	
	initial begin
	#2 x1 <= 1;
	#2 x2 <= 1;
	#2 x1 <= 0;
	#0 x2 <= 0;
	#2 x2 <= 1;
	#0 x3 <= 1;
	#2 x1 <= 0;
	#2 x2 <= 0;
	#0 x3 <= 0;

	end

	initial begin
		$dumpfile("seven.vcd");	
		$dumpvars;
	end	



endmodule

Lab_04/seven.vcd
$date
	Wed May 27 02:43:05 2020
$end
$version
	Icarus Verilog
$end
$timescale
	1ns
$end
$scope module seven_tb $end
$var wire 1 ! z3 $end
$var wire 1 " z2 $end
$var wire 1 # z1 $end
$var wire 3 $ state [2:0] $end
$var reg 1 % clk $end
$var reg 1 & reset $end
$var reg 1 ' x1 $end
$var reg 1 ( x2 $end
$var reg 1 ) x3 $end
$scope module g $end
$var wire 1 % clk $end
$var wire 1 & reset $end
$var wire 1 ' x1 $end
$var wire 1 ( x2 $end
$var wire 1 ) x3 $end
$var wire 1 ! z3 $end
$var wire 1 " z2 $end
$var wire 1 # z1 $end
$var reg 3 * nextstate [2:0] $end
$var reg 3 + state [2:0] $end
$upscope $end
$upscope $end
$enddefinitions $end
#0
$dumpvars
bx +
b0 *
0)
0(
0'
0&
1%
bx $
x#
x"
x!
$end
#1
0%
#2
b1 *
0#
0"
0!
b0 $
b0 +
1'
1%
#3
0%
#4
b10 *
b1 $
b1 +
1(
1%
#5
0%
#6
b0 *
1#
b10 $
b10 +
0(
0'
1%
#7
0%
#8
b101 *
0#
b0 $
b0 +
1)
1(
1%
#9
0%
#10
b100 *
b101 $
b101 +
1%
#11
0%
#12
b0 *
1"
b100 $
b100 +
0)
0(
1%
#13
0%
#14
b101 *
0"
b0 $
b0 +
1%
#15
0%
#16
b111 *
b101 $
b101 +
1%
#17
0%
#18
b0 *
1!
b111 $
b111 +
1%
#19
0%
#20
b101 *
0!
b0 $
b0 +
1%
#21
0%
#22
b111 *
b101 $
b101 +
1%
#23
0%
#24
b0 *
1!
b111 $
b111 +
1%
#25
0%
#26
b101 *
0!
b0 $
b0 +
1%
#27
0%
#28
b111 *
b101 $
b101 +
1%
#29
0%
#30
b0 *
1!
b111 $
b111 +
1%
