Lab_04/thunder.v
module thunder(left, right, reset, clk, la, lb, lc, ra, rb, rc);
	input left, right, reset, clk;
	output la, lb, lc, ra, rb, rc;

	reg [2:0] state, nextstate;

	parameter S0 = 3'b000;
	parameter S1 = 3'b001;
	parameter S2 = 3'b010;
	parameter S3 = 3'b011;
	parameter S4 = 3'b100;
	parameter S5 = 3'b101;
	parameter S6 = 3'b110;
	parameter S7 = 3'b111;

	always @ (posedge clk, posedge reset)
		if (reset)
			state <= S0;
		else
			state <= nextstate;
	always @ (*)
		case (state)
			S0: 	if(left & right)
					nextstate = S7;
				else if (left & ~right)		
					nextstate = S1;
				else if (right & ~left)
					nextstate = S4;	
			     	else
					nextstate = S0;	
			S1: nextstate = S2;
			S2: nextstate = S3;
			S3: nextstate = S0;
			S4: nextstate = S5;
			S5: nextstate = S6;
			S6: nextstate = S0;
			S7: nextstate = S0;
			default: nextstate = S0;
		endcase
	
	assign la = (state == S1 | state == S2 | state == S3 | state == S7);
	assign lb = (state == S2 | state == S3 | state == S7);
	assign lc = (state == S3 | state == S7);
	assign ra = (state == S4 | state == S5 | state == S6 | state == S7);
	assign rb = (state == S5 | state == S6 | state == S7);
	assign rc = (state == S6 | state == S7);
	
			
endmodule

Lab_04/thunder_tb.v
`timescale 1ns/1ns
module thunder_tb;
	reg left, right, reset, clk;
	wire la, lb, lc, ra, rb, rc;
	thunder g(left, right, reset, clk, la, lb, lc, ra, rb, rc);
	initial begin
		$display("time\tclk\treset\tleft\tright\tlc\tlb\tla\tra\trb\trc");
		clk <= 0;
		reset <= 0;
		left <= 0;
		right <= 0;
		#22 $finish;
	end
	initial begin
		$monitor("%2d\t%b\t%b\t%b\t%b\t%b\t%b\t%b\t%b\t%b\t%b", $time, clk, reset, left, right, lc, lb, la, ra, rb, rc);
	end
	
	
	always
	#1 clk <= ~clk;
	
	initial begin
	#3 left <=1;
	#1 left <= 0;
	#6 left <= 0;
	end
	initial begin
	#11 right <= 1;
	#1 right <= 0;
	end

	initial begin
	#19 left <= 1;
	#0 right <= 1; 
	#2 reset <= 1;
	#0 left <= 0;
	#0 right <= 0;
	#1 reset <= 0;
	end
	

	initial begin
		$dumpfile("thunder.vcd");	
		$dumpvars;
	end	






endmodule

Lab_04/thunder.vcd
$date
	Wed May 27 01:00:24 2020
$end
$version
	Icarus Verilog
$end
$timescale
	1ns
$end
$scope module thunder_tb $end
$var wire 1 ! rc $end
$var wire 1 " rb $end
$var wire 1 # ra $end
$var wire 1 $ lc $end
$var wire 1 % lb $end
$var wire 1 & la $end
$var reg 1 ' clk $end
$var reg 1 ( left $end
$var reg 1 ) reset $end
$var reg 1 * right $end
$scope module g $end
$var wire 1 ' clk $end
$var wire 1 & la $end
$var wire 1 % lb $end
$var wire 1 $ lc $end
$var wire 1 ( left $end
$var wire 1 # ra $end
$var wire 1 " rb $end
$var wire 1 ! rc $end
$var wire 1 ) reset $end
$var wire 1 * right $end
$var reg 3 + nextstate [2:0] $end
$var reg 3 , state [2:0] $end
$upscope $end
$upscope $end
$enddefinitions $end
#0
$dumpvars
bx ,
b0 +
0*
0)
0(
0'
x&
x%
x$
x#
x"
x!
$end
#1
0&
0#
0%
0"
0$
0!
b0 ,
1'
#2
0'
#3
1&
b1 ,
b10 +
1'
1(
#4
0'
0(
#5
1%
b11 +
b10 ,
1'
#6
0'
#7
b0 +
1$
b11 ,
1'
#8
0'
#9
0&
0%
0$
b0 ,
1'
#10
0'
#11
1#
b100 ,
b101 +
1'
1*
#12
0'
0*
#13
1"
b110 +
b101 ,
1'
#14
0'
#15
b0 +
1!
b110 ,
1'
#16
0'
#17
0#
0"
0!
b0 ,
1'
#18
0'
#19
1&
1%
1$
1#
1"
1!
b111 ,
b0 +
1*
1'
1(
#20
0'
#21
0&
0%
0$
0#
0"
0!
b0 ,
0*
0(
1'
1)
#22
0)
0'
