Lab_02/decoder/decoder3x8.v
module decoder3x8(n,ena,d);
	input [2:0] n;
	input ena;
	output [7:0]d;

	assign d[0] = (ena==1) ?((n ==3'b000) ? 1: 0):0; 
	assign d[1] = (ena==1) ?((n ==3'b001) ? 1: 0):0;
	assign d[2] = (ena==1) ?((n ==3'b010) ? 1: 0):0; 
	assign d[3] = (ena==1) ?((n ==3'b011) ? 1: 0):0; 
	assign d[4] = (ena==1) ?((n ==3'b100) ? 1: 0):0; 
	assign d[5] = (ena==1) ?((n ==3'b101) ? 1: 0):0; 
	assign d[6] = (ena==1) ?((n ==3'b110) ? 1: 0):0; 
	assign d[7] = (ena==1) ?((n ==3'b111) ? 1: 0):0; 
endmodule

Lab_02/decoder3x8_tb.v
`timescale 1ns/1ns
module decoder3x8_tb	;
	reg [2:0] n;
	reg ena;
	wire [7:0]d;
	decoder3x8 g (n,ena,d);
	initial begin
	$display("time\tena\tn[2]\tn[1]\tn[0]\td[7]\td[6]\td[5]\td[4]\td[3]\td[2]\td[1]\td[0]");

		n = 3'b000;
		ena = 1;		
		#8 $finish;
	end
	initial begin
		$monitor("%2d:\t%b\t%b\t%b\t%b\t%b\t%b\t%b\t%b\t%b\t%b\t%b\t%b",$time,ena,n[2],n[1],n[0],d[7],d[6],d[5],d[4],d[3],d[2],d[1],d[0]);
	end
	always #1 n[0] = !n[0];
	always #2 n[1] = !n[1];
	always #4 n[2] = !n[2];
	always #8 ena = !ena;
	always #8 n = 3'b???;
	
	initial begin
		$dumpfile("decoder3x8.vcd");	
		$dumpvars;
	end	
endmodule

Lab_02/decoder3x8.vcd
$date
	Sat May  2 23:35:26 2020
$end
$version
	Icarus Verilog
$end
$timescale
	1ns
$end
$scope module decoder3x8_tb $end
$var wire 8 ! d [7:0] $end
$var reg 1 " ena $end
$var reg 3 # n [2:0] $end
$scope module g $end
$var wire 1 " ena $end
$var wire 3 $ n [2:0] $end
$var wire 8 % d [7:0] $end
$upscope $end
$upscope $end
$enddefinitions $end
#0
$dumpvars
b1 %
b0 $
b0 #
1"
b1 !
$end
#1
b10 !
b10 %
b1 #
b1 $
#2
b100 !
b100 %
b10 #
b10 $
#3
b1000 !
b1000 %
b11 #
b11 $
#4
b10000 !
b10000 %
b100 #
b100 $
#5
b100000 !
b100000 %
b101 #
b101 $
#6
b1000000 !
b1000000 %
b110 #
b110 $
#7
b10000000 !
b10000000 %
b111 #
b111 $
#8
b0 !
b0 %
bx #
bx $
0"
