Lab_02/demux16_1x16.v
module demux16_1x16(D0, s, y0, y1, y2, y3, y4, y5, y6, y7,y8,y9,y10,y11,y12,y13,y14,y15); 
	input [15:0] D0; 
	input [3:0]s; 
	output [15:0]  y0, y1, y2, y3, y4, y5, y6, y7,y8,y9,y10,y11,y12,y13,y14,y15;
	assign y0 = (s == 4'b0000) ? D0 : 16'b0; 
	assign y1 = (s == 4'b0001) ? D0 : 16'b0; 
	assign y2 = (s == 4'b0010) ? D0 : 16'b0; 
	assign y3 = (s == 4'b0011) ? D0 : 16'b0; 
	assign y4 = (s == 4'b0100) ? D0 : 16'b0; 
	assign y5 = (s == 4'b0101) ? D0 : 16'b0; 
	assign y6 = (s == 4'b0110) ? D0 : 16'b0; 
	assign y7 = (s == 4'b0111) ? D0 : 16'b0;
	assign y8 = (s == 4'b1000) ? D0 : 16'b0; 
	assign y9 = (s == 4'b1001) ? D0 : 16'b0; 
	assign y10 = (s == 4'b1010) ? D0 : 16'b0; 
	assign y11 = (s == 4'b1011) ? D0 : 16'b0; 
	assign y12 = (s == 4'b1100) ? D0 : 16'b0; 
	assign y13 = (s == 4'b1101) ? D0 : 16'b0; 
	assign y14 = (s == 4'b1110) ? D0 : 16'b0; 
	assign y15 = (s == 4'b1111) ? D0 : 16'b0; 
endmodule

Lab_02/demux1x16/demux16_1x16_tb.v
`timescale 1ns/1ns
module demux16_1x16_tb;
	reg [15:0]D0;
	reg [3:0]s;
	wire [15:0]  y0, y1, y2, y3, y4, y5, y6, y7,y8,y9,y10,y11,y12,y13,y14,y15;
	demux16_1x16 g(D0, s, y0, y1, y2, y3, y4, y5, y6, y7,y8,y9,y10,y11,y12,y13,y14,y15);
	initial begin
	$display("time\t\tD0\t\ts\t\ty0\t\t\ty1\t\t\ty2\t\t\ty3\t\t\ty4\t\t\ty5\t\t\ty6\t\t\ty7\t\t\ty8\t\t\ty9\t\t\ty10\t\t\ty11\t\t\ty12\t\t\ty13\t\t\ty14\t\t\ty15");
		D0 = 16'b01;
		s = 4'b0000;
		#16	 $finish;
	end
	initial begin
		$monitor("%2d:\t%b\t%b\t%b\t%b\t%b\t%b\t%b\t%b\t%b\t%b\t%b\t%b\t%b\t%b\t%b\t%b\t%b\t%b",$time,D0, s, y0, y1, y2, y3, y4, y5, y6, y7,y8,y9,y10,y11,y12,y13,y14,y15);
	end
	always #1 s[0] = !s[0];
	always #2 s[1] = !s[1];
	always #4 s[2] = !s[2];
	always #8 s[3] = !s[3];	
	
	initial begin
		$dumpfile("demux16_1x16.vcd");	
		$dumpvars;
	end	
endmodule

Lab_02/demux16_1x16.vcd
$date
	Tue May  5 19:35:12 2020
$end
$version
	Icarus Verilog
$end
$timescale
	1ns
$end
$scope module demux16_1x16_tb $end
$var wire 16 ! y9 [15:0] $end
$var wire 16 " y8 [15:0] $end
$var wire 16 # y7 [15:0] $end
$var wire 16 $ y6 [15:0] $end
$var wire 16 % y5 [15:0] $end
$var wire 16 & y4 [15:0] $end
$var wire 16 ' y3 [15:0] $end
$var wire 16 ( y2 [15:0] $end
$var wire 16 ) y15 [15:0] $end
$var wire 16 * y14 [15:0] $end
$var wire 16 + y13 [15:0] $end
$var wire 16 , y12 [15:0] $end
$var wire 16 - y11 [15:0] $end
$var wire 16 . y10 [15:0] $end
$var wire 16 / y1 [15:0] $end
$var wire 16 0 y0 [15:0] $end
$var reg 16 1 D0 [15:0] $end
$var reg 4 2 s [3:0] $end
$scope module g $end
$var wire 16 3 D0 [15:0] $end
$var wire 4 4 s [3:0] $end
$var wire 16 5 y9 [15:0] $end
$var wire 16 6 y8 [15:0] $end
$var wire 16 7 y7 [15:0] $end
$var wire 16 8 y6 [15:0] $end
$var wire 16 9 y5 [15:0] $end
$var wire 16 : y4 [15:0] $end
$var wire 16 ; y3 [15:0] $end
$var wire 16 < y2 [15:0] $end
$var wire 16 = y15 [15:0] $end
$var wire 16 > y14 [15:0] $end
$var wire 16 ? y13 [15:0] $end
$var wire 16 @ y12 [15:0] $end
$var wire 16 A y11 [15:0] $end
$var wire 16 B y10 [15:0] $end
$var wire 16 C y1 [15:0] $end
$var wire 16 D y0 [15:0] $end
$upscope $end
$upscope $end
$enddefinitions $end
#0
$dumpvars
b1 D
b0 C
b0 B
b0 A
b0 @
b0 ?
b0 >
b0 =
b0 <
b0 ;
b0 :
b0 9
b0 8
b0 7
b0 6
b0 5
b0 4
b1 3
b0 2
b1 1
b1 0
b0 /
b0 .
b0 -
b0 ,
b0 +
b0 *
b0 )
b0 (
b0 '
b0 &
b0 %
b0 $
b0 #
b0 "
b0 !
$end
#1
b0 0
b0 D
b1 /
b1 C
b1 2
b1 4
#2
b1 (
b1 <
b0 /
b0 C
b10 2
b10 4
#3
b0 (
b0 <
b1 '
b1 ;
b11 2
b11 4
#4
b1 &
b1 :
b0 '
b0 ;
b100 2
b100 4
#5
b0 &
b0 :
b1 %
b1 9
b101 2
b101 4
#6
b1 $
b1 8
b0 %
b0 9
b110 2
b110 4
#7
b0 $
b0 8
b1 #
b1 7
b111 2
b111 4
#8
b1 "
b1 6
b0 #
b0 7
b1000 2
b1000 4
#9
b0 "
b0 6
b1 !
b1 5
b1001 2
b1001 4
#10
b1 .
b1 B
b0 !
b0 5
b1010 2
b1010 4
#11
b0 .
b0 B
b1 -
b1 A
b1011 2
b1011 4
#12
b1 ,
b1 @
b0 -
b0 A
b1100 2
b1100 4
#13
b0 ,
b0 @
b1 +
b1 ?
b1101 2
b1101 4
#14
b1 *
b1 >
b0 +
b0 ?
b1110 2
b1110 4
#15
b0 *
b0 >
b1 )
b1 =
b1111 2
b1111 4
#16
b1 0
b1 D
b0 )
b0 =
b0 2
b0 4
