Lab_02/encoder8x3.v
module encoder8x3 (d,ena,n);
	input [7:0]d;
	input ena;
	output [2:0]n;
	reg [2:0]n;
	always @(d,ena) begin	
	if(ena==1)begin	
	casex(d)
	8'b1??????? : n = 3'b111;
	8'b01?????? : n = 3'b110;
	8'b001????? : n = 3'b101;
	8'b0001???? : n = 3'b100;
	8'b00001??? : n = 3'b011;
	8'b000001?? : n = 3'b010;
	8'b0000001? : n = 3'b001;
	8'b00000001 : n = 3'b000;
	default: n = 3'b000;
	endcase
	end
	else begin n = 3'b000;end
end
endmodule

Lab_02/encoder8x3_tb.v
`timescale 1ns/1ns
module encoder8x3_tb;
	reg [7:0] d;
	reg ena;
	wire [2:0]n;
	encoder8x3 g (d,ena,n);
	initial begin
	$display("time\tena\td[7]\td[6]\td[5]\td[4]\td[3]\td[2]\td[1]\td[0]\tn[2]\tn[1]\tn[0]");
		d= 8'b00;
		ena = 1;		
		#9 $finish;
	end
	initial begin
		$monitor("%2d:\t%b\t%b\t%b\t%b\t%b\t%b\t%b\t%b\t%b\t%b\t%b\t%b",$time,ena,d[7],d[6],d[5],d[4],d[3],d[2],d[1],d[0],n[2],n[1],n[0]);
	end
	initial begin	
	#1 d = 8'b1;	
	#1 d = 8'b1X;	
	#1 d = 8'b1XX;	
	#1 d = 8'b1XXX;	
	#1 d = 8'b1XXXX;	
	#1 d = 8'b1XXXXX;	
	#1 d = 8'b1XXXXXX;	
	#1 d = 8'b1XXXXXXX;	
	#8 d = 8'bXXXXXXXX;
	end	
	always #9 ena = !ena;
	always #9 d = 8'bXXXXXXXX;
	initial begin
		$dumpfile("encoder8x3.vcd");	
		$dumpvars;
	end	
endmodule

Lab_02/encoder8x3.vcd
$date
	Sun May  3 12:25:43 2020
$end
$version
	Icarus Verilog
$end
$timescale
	1ns
$end
$scope module encoder8x3_tb $end
$var wire 3 ! n [2:0] $end
$var reg 8 " d [7:0] $end
$var reg 1 # ena $end
$scope module g $end
$var wire 8 $ d [7:0] $end
$var wire 1 # ena $end
$var reg 3 % n [2:0] $end
$upscope $end
$upscope $end
$enddefinitions $end
#0
$dumpvars
b0 %
b0 $
1#
b0 "
b0 !
$end
#1
b1 "
b1 $
#2
b1 !
b1 %
b1x "
b1x $
#3
b10 !
b10 %
b1xx "
b1xx $
#4
b11 !
b11 %
b1xxx "
b1xxx $
#5
b100 !
b100 %
b1xxxx "
b1xxxx $
#6
b101 !
b101 %
b1xxxxx "
b1xxxxx $
#7
b110 !
b110 %
b1xxxxxx "
b1xxxxxx $
#8
b111 !
b111 %
b1xxxxxxx "
b1xxxxxxx $
#9
b0 !
b0 %
bx "
bx $
0#
