Lab_02/mux8x1/mux16_8x1_or.v
module mux16_8x1_or(l, m, n, o, p, q, r, s, t);
	output [15:0]l;
	input [15:0]m, n, o, p, q, r, s, t;
assign l = m | n | o | p | q | r | s | t;
endmodule

Lab_02/mux16_8x1_and.v
module mux16_8x1_and(a, b, c, d, e);
	output [15:0]a;
	input [15:0]b;
	input c,d,e;
	wire validacion;
	assign validacion = (c & d & e);
assign a = validacion? b: 16'b00;
endmodule

Lab_02/mux16_8x1_not.v
module mux16_8x1_not(f,h);
	output f;
	input h;
assign f = ~h;
endmodule

Lab_02/mux16_8x1.v
module mux16_8x1(D0, D1, D2, D3, D4, D5, D6, D7, S0, S1, S2, out); 
output [15:0]out; 
input [15:0] D0,D1,D2, D3,D4,D5,D6,D7;
input S0,S1,S2; 
input NS0, NS1, NS2;
wire [15:0]T1, T2, T3, T4, T5, T6, T7, T8;

mux16_8x1_not a1(NS0, S0);
mux16_8x1_not a2(NS1, S1);
mux16_8x1_not a3(NS2, S2);

mux16_8x1_and u1(T1, D0, NS0, NS1, NS2);
mux16_8x1_and u2(T2, D1, S0, NS1, NS2);
mux16_8x1_and u3(T3, D2, NS0, S1, NS2);
mux16_8x1_and u4(T4, D3, S0, S1, NS2);
mux16_8x1_and u5(T5, D4, NS0, NS1, S2);
mux16_8x1_and u6(T6, D5, S0, NS1, S2);
mux16_8x1_and u7(T7, D6, NS0, S1, S2);
mux16_8x1_and u8(T8, D7, S0, S1, S2);
mux16_8x1_or u12(out, T1, T2, T3, T4, T5, T6, T7, T8);
endmodule

Lab_02/mux16_8x1_tb.v
`timescale 1ns/1ns
module mux16_8x1_tb;
    wire[15:0]out;
    	reg  [15:0]D0, D1, D2, D3, D4, D5, D6, D7;
	reg S0, S1, S2;

    mux16_8x1 g (D0, D1, D2, D3, D4, D5, D6, D7, S0, S1, S2, out);
    initial begin
		D0 = 16'b000;
		D1 = 16'b001;
		D2 = 16'b010;
		D3 = 16'b011;
		D4 = 16'b100;
		D5 = 16'b101;
		D6 = 16'b110;
		D7 = 16'b111;
		S0 = 0;
		S1 = 0;
		S2 = 0;
		$display("time\t\tD0\t\t\tD1\t\t\tD2\t\t\tD3\t\t\tD4\t\t\tD5\t\t\tD6\t\t\tD7\t\tS2\tS1\tS0\t\tY"); 
		$monitor("%2d:\t%b\t%b\t%b\t%b\t%b\t%b\t%b\t%b\t%b\t%b\t%b\t%b",$time,D0, D1, D2, D3, D4, D5, D6, D7, S2, S1, S0, out);
    		   #8 $finish;
    end
always #1 S0 = !S0;
always #2 S1 = !S1;
always #4 S2 = !S2;
    initial begin 
        $dumpfile("mux16_8x1.vcd"); 
        $dumpvars;
    end
endmodule

Lab_02/mux16_8x1.vcd
$date
	Tue May  5 19:35:05 2020
$end
$version
	Icarus Verilog
$end
$timescale
	1ns
$end
$scope module mux16_8x1_tb $end
$var wire 16 ! out [15:0] $end
$var reg 16 " D0 [15:0] $end
$var reg 16 # D1 [15:0] $end
$var reg 16 $ D2 [15:0] $end
$var reg 16 % D3 [15:0] $end
$var reg 16 & D4 [15:0] $end
$var reg 16 ' D5 [15:0] $end
$var reg 16 ( D6 [15:0] $end
$var reg 16 ) D7 [15:0] $end
$var reg 1 * S0 $end
$var reg 1 + S1 $end
$var reg 1 , S2 $end
$scope module g $end
$var wire 16 - D0 [15:0] $end
$var wire 16 . D1 [15:0] $end
$var wire 16 / D2 [15:0] $end
$var wire 16 0 D3 [15:0] $end
$var wire 16 1 D4 [15:0] $end
$var wire 16 2 D5 [15:0] $end
$var wire 16 3 D6 [15:0] $end
$var wire 16 4 D7 [15:0] $end
$var wire 1 * S0 $end
$var wire 1 + S1 $end
$var wire 1 , S2 $end
$var wire 16 5 out [15:0] $end
$var wire 16 6 T8 [15:0] $end
$var wire 16 7 T7 [15:0] $end
$var wire 16 8 T6 [15:0] $end
$var wire 16 9 T5 [15:0] $end
$var wire 16 : T4 [15:0] $end
$var wire 16 ; T3 [15:0] $end
$var wire 16 < T2 [15:0] $end
$var wire 16 = T1 [15:0] $end
$var wire 1 > NS2 $end
$var wire 1 ? NS1 $end
$var wire 1 @ NS0 $end
$scope module a1 $end
$var wire 1 @ f $end
$var wire 1 * h $end
$upscope $end
$scope module a2 $end
$var wire 1 ? f $end
$var wire 1 + h $end
$upscope $end
$scope module a3 $end
$var wire 1 > f $end
$var wire 1 , h $end
$upscope $end
$scope module u1 $end
$var wire 16 A b [15:0] $end
$var wire 1 @ c $end
$var wire 1 ? d $end
$var wire 1 > e $end
$var wire 1 B validacion $end
$var wire 16 C a [15:0] $end
$upscope $end
$scope module u12 $end
$var wire 16 D l [15:0] $end
$var wire 16 E m [15:0] $end
$var wire 16 F t [15:0] $end
$var wire 16 G s [15:0] $end
$var wire 16 H r [15:0] $end
$var wire 16 I q [15:0] $end
$var wire 16 J p [15:0] $end
$var wire 16 K o [15:0] $end
$var wire 16 L n [15:0] $end
$upscope $end
$scope module u2 $end
$var wire 16 M b [15:0] $end
$var wire 1 * c $end
$var wire 1 ? d $end
$var wire 1 > e $end
$var wire 1 N validacion $end
$var wire 16 O a [15:0] $end
$upscope $end
$scope module u3 $end
$var wire 16 P b [15:0] $end
$var wire 1 @ c $end
$var wire 1 + d $end
$var wire 1 > e $end
$var wire 1 Q validacion $end
$var wire 16 R a [15:0] $end
$upscope $end
$scope module u4 $end
$var wire 16 S b [15:0] $end
$var wire 1 * c $end
$var wire 1 + d $end
$var wire 1 > e $end
$var wire 1 T validacion $end
$var wire 16 U a [15:0] $end
$upscope $end
$scope module u5 $end
$var wire 16 V b [15:0] $end
$var wire 1 @ c $end
$var wire 1 ? d $end
$var wire 1 , e $end
$var wire 1 W validacion $end
$var wire 16 X a [15:0] $end
$upscope $end
$scope module u6 $end
$var wire 16 Y b [15:0] $end
$var wire 1 * c $end
$var wire 1 ? d $end
$var wire 1 , e $end
$var wire 1 Z validacion $end
$var wire 16 [ a [15:0] $end
$upscope $end
$scope module u7 $end
$var wire 16 \ b [15:0] $end
$var wire 1 @ c $end
$var wire 1 + d $end
$var wire 1 , e $end
$var wire 1 ] validacion $end
$var wire 16 ^ a [15:0] $end
$upscope $end
$scope module u8 $end
$var wire 16 _ b [15:0] $end
$var wire 1 * c $end
$var wire 1 + d $end
$var wire 1 , e $end
$var wire 1 ` validacion $end
$var wire 16 a a [15:0] $end
$upscope $end
$upscope $end
$upscope $end
$enddefinitions $end
#0
$dumpvars
b0 a
0`
b111 _
b0 ^
0]
b110 \
b0 [
0Z
b101 Y
b0 X
0W
b100 V
b0 U
0T
b11 S
b0 R
0Q
b10 P
b0 O
0N
b1 M
b0 L
b0 K
b0 J
b0 I
b0 H
b0 G
b0 F
b0 E
b0 D
b0 C
1B
b0 A
1@
1?
1>
b0 =
b0 <
b0 ;
b0 :
b0 9
b0 8
b0 7
b0 6
b0 5
b111 4
b110 3
b101 2
b100 1
b11 0
b10 /
b1 .
b0 -
0,
0+
0*
b111 )
b110 (
b101 '
b100 &
b11 %
b10 $
b1 #
b0 "
b0 !
$end
#1
b1 !
b1 5
b1 D
0B
b1 <
b1 L
b1 O
1N
0@
1*
#2
b10 !
b10 5
b10 D
b10 ;
b10 K
b10 R
1Q
b0 <
b0 L
b0 O
0N
1@
0?
0*
1+
#3
b11 !
b11 5
b11 D
b0 ;
b0 K
b0 R
0Q
b11 :
b11 J
b11 U
1T
0@
1*
#4
b100 9
b100 I
b100 X
1W
b0 :
b0 J
b0 U
b100 !
b100 5
b100 D
0T
b0 6
b0 F
b0 a
1@
1?
0>
0`
0*
0+
1,
#5
b101 !
b101 5
b101 D
b0 9
b0 I
b0 X
0W
b101 8
b101 H
b101 [
1Z
0@
1*
#6
b110 !
b110 5
b110 D
b110 7
b110 G
b110 ^
1]
b0 8
b0 H
b0 [
0Z
1@
0?
0*
1+
#7
b0 7
b0 G
b0 ^
b111 !
b111 5
b111 D
0]
b111 6
b111 F
b111 a
1`
0@
1*
#8
1B
b0 !
b0 5
b0 D
b0 6
b0 F
b0 a
1@
1?
1>
0`
0*
0+
0,
