Lab_02/mux16_2x1.v
module mux16_2x1(a, b, s, y);
	input 	[15:0] a;
	input 	[15:0] b;
	input 	s;

	output [15:0]y;

	assign y = s? b : a;
endmodule

Lab_02/mux2x1/mux16_2x1_tb.v
`timescale 1ns/1ns
module mux16_2x1_tb;
	reg s;
	reg [15:0] a,b;
	wire  [15:0]y;
	mux16_2x1 g (a,b,s,y);
	initial begin
	$display("time\t\ta\t\t\tb\t\ts\t\ty");
		a = 16'b1111000011110000;
		b = 16'b0000111100001111;
		s = 16'b00;
		#10 $finish;
	end
	initial begin
		$monitor("%2d:\t%b\t%b\t%b\t%b",$time,a,b,s,y);
	end
	always #1 a = a - 1;
	always #1 s = !s;
	always #2 b = b + 1;	
	
	initial begin
		$dumpfile("mux16_2x1.vcd");	
		$dumpvars;
	end	
endmodule

Lab_02/mux16_2x1.vcd
$date
	Tue May  5 19:35:03 2020
$end
$version
	Icarus Verilog
$end
$timescale
	1ns
$end
$scope module mux16_2x1_tb $end
$var wire 16 ! y [15:0] $end
$var reg 16 " a [15:0] $end
$var reg 16 # b [15:0] $end
$var reg 1 $ s $end
$scope module g $end
$var wire 16 % a [15:0] $end
$var wire 16 & b [15:0] $end
$var wire 1 $ s $end
$var wire 16 ' y [15:0] $end
$upscope $end
$upscope $end
$enddefinitions $end
#0
$dumpvars
b1111000011110000 '
b111100001111 &
b1111000011110000 %
0$
b111100001111 #
b1111000011110000 "
b1111000011110000 !
$end
#1
b111100001111 !
b111100001111 '
1$
b1111000011101111 "
b1111000011101111 %
#2
b1111000011101110 !
b1111000011101110 '
0$
b1111000011101110 "
b1111000011101110 %
b111100010000 #
b111100010000 &
#3
b111100010000 !
b111100010000 '
1$
b1111000011101101 "
b1111000011101101 %
#4
b1111000011101100 !
b1111000011101100 '
0$
b1111000011101100 "
b1111000011101100 %
b111100010001 #
b111100010001 &
#5
b111100010001 !
b111100010001 '
1$
b1111000011101011 "
b1111000011101011 %
#6
b1111000011101010 !
b1111000011101010 '
0$
b1111000011101010 "
b1111000011101010 %
b111100010010 #
b111100010010 &
#7
b111100010010 !
b111100010010 '
1$
b1111000011101001 "
b1111000011101001 %
#8
b1111000011101000 !
b1111000011101000 '
0$
b1111000011101000 "
b1111000011101000 %
b111100010011 #
b111100010011 &
#9
b111100010011 !
b111100010011 '
1$
b1111000011100111 "
b1111000011100111 %
#10
b1111000011100110 !
b1111000011100110 '
0$
b1111000011100110 "
b1111000011100110 %
b111100010100 #
b111100010100 &
