Lab_03/btff.v
module btff(prn, t, clk, clrn, q, qn);
	input prn, t, clk, clrn;
	output reg q, qn;

always @(posedge clk)
begin
	if(clrn == 1 & prn == 0)
	begin
		q <= 1;
		qn <= 0;
	end
	else if(clrn == 0 & prn == 1)
	begin
		q <= 0;
		qn <= 1;
	end
	else if (clrn == 0 & prn == 0)
	begin
		q <= 1'bX;
		qn <= 1'bX;
	end
	else
	begin
		if(t)
		begin
			q <= ~q;
			qn <= ~qn;		
		end
	end
end


endmodule

Lab_03/btff_tb.v
`timescale 1ns/1ns
module btff_tb;
	reg prn, t, clk, clrn;
	wire q, qn;
	btff g(prn, t, clk, clrn, q, qn);
	initial begin
		$display("time\tprn\tt\tclk\tclrn\tq\tqn");
		prn <= 1;
		clrn <= 0;
		clk <= 1;
		t <= 1;
		#23 $finish;
	end
	initial begin
		$monitor("%2d\t%b\t%b\t%b\t%b\t%b\t%b", $time, prn, t, clk, clrn, q, qn);
	end
	
	initial begin
	#1 clrn <= 1;
	#2 t <= ~t;
	#2 t <=	~t;
	#10 t <= ~t;	
	#2 t <= ~t;	
	end
	
	always
	#1 clk <= ~clk;

	initial begin
		$dumpfile("btlatch.vcd");	
		$dumpvars;
	end	
endmodule

Lab_03/btff.vcd
$date
	Fri May 15 01:13:54 2020
$end
$version
	Icarus Verilog
$end
$timescale
	1ns
$end
$scope module btff_tb $end
$var wire 1 ! qn $end
$var wire 1 " q $end
$var reg 1 # clk $end
$var reg 1 $ clrn $end
$var reg 1 % prn $end
$var reg 1 & t $end
$scope module g $end
$var wire 1 # clk $end
$var wire 1 $ clrn $end
$var wire 1 % prn $end
$var wire 1 & t $end
$var reg 1 " q $end
$var reg 1 ! qn $end
$upscope $end
$upscope $end
$enddefinitions $end
#0
$dumpvars
1&
1%
0$
1#
0"
1!
$end
#1
0#
1$
#2
0!
1"
1#
#3
0#
0&
#4
1#
#5
0#
1&
#6
1!
0"
1#
#7
0#
#8
0!
1"
1#
#9
0#
#10
1!
0"
1#
#11
0#
#12
0!
1"
1#
#13
0#
#14
1!
0"
1#
#15
0#
0&
#16
1#
#17
0#
1&
#18
0!
1"
1#
#19
0#
#20
1!
0"
1#
#21
0#
#22
0!
1"
1#
