Verilog_Lab07/mipsmem.v
//------------------------------------------------
// mipsmemsingle.sv
// Updated to SystemVerilog - Harris Harris version
// External memories used by MIPS single-cycle
// processor
//------------------------------------------------

module dmem(input          clk, we,
            input   [31:0] a, wd,
            output  [31:0] rd);

   reg [31:0] RAM[63:0];

  assign rd = RAM[a[31:2]]; // word aligned

  always @(posedge clk)
    if (we)
      RAM[a[31:2]] <= wd;
endmodule

module imem(input   [5:0]  a,
            output  [31:0] rd);

   reg [31:0] RAM[63:0];

  initial
    begin
      $readmemh("memfile.dat", RAM,0,17); // initialize memory
    end

  assign rd = RAM[a]; // word aligned
endmodule

Verilog_Lab07/ALU.v
module Adder #(parameter n = 32)(a, b, s, y);
	input [n-1:0] a, b;
	input s;
	output reg[n-1:0] y;
	always @(*)begin
	case(s)
	1'b1:	y <= a + b + 1;
	1'b0:	y <= a + b;
	endcase
end	
endmodule

module mux2x1  #(parameter n = 32)(a, b, s, y);
	input [n-1:0] a, b;
	input s;
	output [n-1:0]y;
	assign y = s? b : a;
endmodule


module adder_substractor #(parameter n = 32)(a, b, s, y);
	input [n-1:0] a, b;
	input s;
	wire [n-1:0] con;
	output [n-1:0] y;
	mux2x1 #(.n(n)) first_mux(b, ~b, s, con);
	Adder  #(.n(n)) first_adder(a, con, s, y);
endmodule

module stl  #(parameter n = 32)(a, s, y);
	input [n-1:0] a;
	input s;
	reg [n-1:0] extend;
	output [n-1:0] y;
	always @(*)begin
		extend = {n{a[n-1]}};	
	end

	mux2x1 #(.n(n)) first_mux(a, extend, s, y);
endmodule

module a_part  #(parameter n = 32)(a, b, op1, op3, arithout);
	input [n-1:0] a, b;
	input op1, op3;
	wire [n-1:0] addout;
	output [n-1:0] arithout;
	adder_substractor #(.n(n)) first_adder_substractor(a, b, op1, addout);
	stl #(.n(n)) first_stl(addout, op3, arithout);
endmodule

module l_part #(parameter n = 32)(a, b, op, logicout);
	input [n-1:0] a, b;
	input [3:0] op;
	output reg[n-1:0] logicout;

	always @ (op) begin
		case(op)
		4'b0100	:	logicout = a & b;	
		4'b0101	:	logicout = a | b;
		4'b0110	:	logicout = a ^ b;
		4'b0111	:	logicout = a ~| b;
		default :	logicout = 'bX;
		endcase
	end
endmodule	

module cero #(parameter n = 32)(a, y);
	input [n-1:0] a;
	output reg y;
	always @(*)begin
	if(a==32'b0)
	begin
		y = 1;
	end	
	else
	begin
		y = 0;
	end
	end
endmodule


module alu #(parameter n = 32)(a, b, op, result, cero);
	input [n-1:0] a, b;
	input [3:0] op;
	output [n-1:0] result;
	output cero;
	wire [n-1:0]arithout, logicout;

		a_part #(.n(n)) a_block(a, b, op[1], op[3], arithout);
		l_part #(.n(n)) l_block(a, b, op, logicout);
		mux2x1 #(.n(n)) answer(arithout, logicout, op[2], result);
		cero #(.n(n)) z_block(result, cero);
endmodule

Verilog_Lab07/mips.v
//--------------------------------------------------------------
// mips.sv
// Updated to SystemVerilog - Harris Harris version
// Single-cycle MIPS processor
//--------------------------------------------------------------

// files needed for simulation:
//  mipsttest.v
//  mipstop.v
//  mipsmem.v
//  mips.v
//  mipsparts.v

// single-cycle MIPS processor
module mips(input          clk, reset,
            output  [31:0] pc,
            input   [31:0] instr,
            output         memwrite,
            output  [31:0] aluout, writedata,
            input   [31:0] readdata);

  wire        memtoreg, branch,
               pcsrc, zero,
               alusrc, regdst, regwrite, jump;
   wire	 [3:0]  alucontrol;

  controller c(instr[31:26], instr[5:0], zero,
               memtoreg, memwrite, pcsrc,
               alusrc, regdst, regwrite, jump,
               alucontrol);
  datapath dp(clk, reset, memtoreg, pcsrc,
              alusrc, regdst, regwrite, jump,
              alucontrol,
              zero, pc, instr,
              aluout, writedata, readdata);
endmodule

module controller(input   [5:0] op, funct,
                  input         zero,
                  output        memtoreg, memwrite,
                  output        pcsrc, alusrc,
                  output        regdst, regwrite,
                  output        jump,
                  output  [3:0] alucontrol);

   wire [1:0] aluop;
   wire      branch;

  maindec md(op, memtoreg, memwrite, branch,
             alusrc, regdst, regwrite, jump,
             aluop);
  aludec  ad(funct, aluop, alucontrol);

  assign pcsrc = branch & zero;
endmodule

module maindec(input   [5:0] op,
               output        memtoreg, memwrite,
               output        branch, alusrc,
               output        regdst, regwrite,
               output        jump,
               output  [1:0] aluop);

   reg [8:0] controls;

  assign {regwrite, regdst, alusrc,
          branch, memwrite,
          memtoreg, jump, aluop} = controls;

  always @(*)
    case(op)
      6'b000000: controls <= 9'b110000010; //Rtype
      6'b100011: controls <= 9'b101001000; //LW
      6'b101011: controls <= 9'b001010000; //SW
      6'b000100: controls <= 9'b000100001; //BEQ
      6'b001000: controls <= 9'b101000000; //ADDI
      6'b000010: controls <= 9'b000000100; //J
      default:   controls <= 9'bxxxxxxxxx; //???
    endcase
endmodule

module aludec(input   [5:0] funct,
              input   [1:0] aluop,
              output reg  [3:0] alucontrol);

  always @(*)
    case(aluop)
      2'b00: alucontrol <= 4'b0000;  // add
      2'b01: alucontrol <= 4'b0010;  // sub
      default: case(funct)          // RTYPE
          6'b100000: alucontrol <= 4'b0000; // ADD
          6'b100010: alucontrol <= 4'b0010; // SUB
          6'b100100: alucontrol <= 4'b0100; // AND
          6'b100101: alucontrol <= 4'b0101; // OR
          6'b101010: alucontrol <= 4'b1010; // SLT
          default:   alucontrol <= 4'bxxxx; // ???
        endcase
    endcase
endmodule

module datapath(input          clk, reset,
                input          memtoreg, pcsrc,
                input          alusrc, regdst,
                input          regwrite, jump,
                input   [3:0]  alucontrol,
                output         zero,
                output  [31:0] pc,
                input   [31:0] instr,
                output  [31:0] aluout, writedata,
                input   [31:0] readdata);

   wire [4:0]  writereg;
   wire [31:0] pcnext, pcnextbr, pcplus4, pcbranch;
   wire [31:0] signimm, signimmsh;
   wire [31:0] srca, srcb;
   wire [31:0] result;

  // next PC 
  flopr #(32) pcreg(clk, reset, pcnext, pc);
  adder       pcadd1(pc, 32'b100, pcplus4);
  sl2         immsh(signimm, signimmsh);
  adder       pcadd2(pcplus4, signimmsh, pcbranch);
  mux2 #(32)  pcbrmux(pcplus4, pcbranch, pcsrc,
                      pcnextbr);
  mux2 #(32)  pcmux(pcnextbr, {pcplus4[31:28], 
                    instr[25:0], 2'b00}, 
                    jump, pcnext);

  // register file 
  regfile     rf(clk, regwrite, instr[25:21],
                 instr[20:16], writereg,
                 result, srca, writedata);
  mux2 #(5)   wrmux(instr[20:16], instr[15:11],
                    regdst, writereg);
  mux2 #(32)  resmux(aluout, readdata,
                     memtoreg, result);
  signext     se(instr[15:0], signimm);

  // ALU 
  mux2 #(32)  srcbmux(writedata, signimm, alusrc,
                      srcb);
  alu         alu(srca, srcb, alucontrol,
                  aluout, zero);
                  
endmodule

Proyecto/Lab_07/mipstop.v
// Top level system including MIPS and memories
//------------------------------------------------
module top(input         clk, reset, 
           output [31:0] writedata, dataadr, 
           output        memwrite);

  wire [31:0] pc, instr, readdata;
  
  // instantiate processor and memories
  mips mips(clk, reset, pc, instr, memwrite, dataadr, writedata, readdata);
  imem imem(pc[7:2], instr);
  dmem dmem(clk, memwrite, dataadr, writedata, readdata);

endmodule

Verilog_Lab07/mipstest.v
//------------------------------------------------
// mipstest.sv
// Updated to SystemVerilog - Harris Harris version
// Testbench for MIPS processor
//------------------------------------------------

module testbench();

  reg        clk;
  reg        reset;

  wire [31:0] writedata, dataadr;
  wire        memwrite;

  // instantiate device to be tested
  top dut(clk, reset, writedata, dataadr, memwrite);
  
  // initialize test
  initial
    begin
      reset <= 1; # 22; reset <=0;
    end

  // generate clock to sequence tests
  always
    begin
      clk <= 1; # 5;
      clk <= 0; # 5;
    end

  // check that 7 gets written to address 84
  always@(negedge clk)
    begin
    $display("ADDRESS  --   ", dataadr);
    $display("WRITEDATA --   ", writedata);
     $display("MEMWRITE --   ", memwrite);
     $display("CLK --   ", clk);
     $display("RESET --   ", reset);
    $display("\n");
      if(memwrite) begin
        if(dataadr === 84 & writedata === 7) begin
          $display("Simulation succeeded");
          $stop;
        end else if (dataadr !== 80) begin
          $display("Simulation failed");
          $stop;
        end
      end
    end
     initial begin
                $dumpfile("lab07.vcd");   
                $dumpvars;
        end     
endmodule

Verilog_Lab07/mipsparts.v
//------------------------------------------------
// mipsparts.sv
// Updated to SystemVerilog - Harris Harris version
// Components used in MIPS processor
//------------------------------------------------

module regfile(input          clk, 
               input          we3, 
               input   [4:0]  ra1, ra2, wa3, 
               input   [31:0] wd3, 
               output  [31:0] rd1, rd2);

  reg [31:0] rf[31:0];

  // three ported register file
  // read two ports combinationally
  // write third port on rising edge of clock
  // register 0 hardwired to 0

  always@(posedge clk)
    if (we3) rf[wa3] <= wd3;	

  assign rd1 = (ra1 != 0) ? rf[ra1] : 0;
  assign rd2 = (ra2 != 0) ? rf[ra2] : 0;
endmodule

module adder(input   [31:0] a, b,
             output [31:0] y);

  assign y = a + b;
endmodule

module sl2(input  [31:0] a,
           output [31:0] y);

  // shift left by 2
  assign y = {a[29:0], 2'b00};
endmodule

module signext(input   [15:0] a,
               output  [31:0] y);
              
  assign y = {{16{a[15]}}, a};
endmodule

module flopr #(parameter WIDTH = 8)
              (input               clk, reset,
               input  [WIDTH-1:0] d, 
               output  reg [WIDTH-1:0] q);

  always@(posedge clk, posedge reset)
  begin
    if (reset) q <= 0;
    else       q <= d;
  end
endmodule

module flopenr #(parameter WIDTH = 8)
                (input               clk, reset,
                 input               en,
                 input   [WIDTH-1:0] d, 
                 output reg [WIDTH-1:0] q);
 
  always @(posedge clk, posedge reset)
  begin
    if      (reset) q <= 0;
    else if (en)    q <= d;
  end
endmodule

module mux2 #(parameter WIDTH = 8)
             (input   [WIDTH-1:0] d0, d1, 
              input               s, 
              output  [WIDTH-1:0] y);

  assign y = s ? d1 : d0; 
endmodule

Verilog_Lab07/lab07.vcd
$date
	Fri Jul 10 22:28:32 2020
$end
$version
	Icarus Verilog
$end
$timescale
	1s
$end
$scope module flopenr $end
$var wire 1 ! clk $end
$var wire 8 " d [7:0] $end
$var wire 1 # en $end
$var wire 1 $ reset $end
$var reg 8 % q [7:0] $end
$upscope $end
$scope module testbench $end
$var wire 32 & writedata [31:0] $end
$var wire 1 ' memwrite $end
$var wire 32 ( dataadr [31:0] $end
$var reg 1 ) clk $end
$var reg 1 * reset $end
$scope module dut $end
$var wire 1 ) clk $end
$var wire 1 * reset $end
$var wire 32 + writedata [31:0] $end
$var wire 32 , readdata [31:0] $end
$var wire 32 - pc [31:0] $end
$var wire 1 ' memwrite $end
$var wire 32 . instr [31:0] $end
$var wire 32 / dataadr [31:0] $end
$scope module dmem $end
$var wire 1 ) clk $end
$var wire 32 0 rd [31:0] $end
$var wire 1 ' we $end
$var wire 32 1 wd [31:0] $end
$var wire 32 2 a [31:0] $end
$upscope $end
$scope module imem $end
$var wire 6 3 a [5:0] $end
$var wire 32 4 rd [31:0] $end
$upscope $end
$scope module mips $end
$var wire 1 ) clk $end
$var wire 32 5 instr [31:0] $end
$var wire 32 6 readdata [31:0] $end
$var wire 1 * reset $end
$var wire 1 7 zero $end
$var wire 32 8 writedata [31:0] $end
$var wire 1 9 regwrite $end
$var wire 1 : regdst $end
$var wire 1 ; pcsrc $end
$var wire 32 < pc [31:0] $end
$var wire 1 ' memwrite $end
$var wire 1 = memtoreg $end
$var wire 1 > jump $end
$var wire 1 ? alusrc $end
$var wire 32 @ aluout [31:0] $end
$var wire 4 A alucontrol [3:0] $end
$scope module c $end
$var wire 6 B funct [5:0] $end
$var wire 6 C op [5:0] $end
$var wire 1 ; pcsrc $end
$var wire 1 7 zero $end
$var wire 1 9 regwrite $end
$var wire 1 : regdst $end
$var wire 1 ' memwrite $end
$var wire 1 = memtoreg $end
$var wire 1 > jump $end
$var wire 1 D branch $end
$var wire 1 ? alusrc $end
$var wire 2 E aluop [1:0] $end
$var wire 4 F alucontrol [3:0] $end
$scope module ad $end
$var wire 6 G funct [5:0] $end
$var wire 2 H aluop [1:0] $end
$var reg 4 I alucontrol [3:0] $end
$upscope $end
$scope module md $end
$var wire 6 J op [5:0] $end
$var wire 1 9 regwrite $end
$var wire 1 : regdst $end
$var wire 1 ' memwrite $end
$var wire 1 = memtoreg $end
$var wire 1 > jump $end
$var wire 1 D branch $end
$var wire 1 ? alusrc $end
$var wire 2 K aluop [1:0] $end
$var reg 9 L controls [8:0] $end
$upscope $end
$upscope $end
$scope module dp $end
$var wire 4 M alucontrol [3:0] $end
$var wire 1 ? alusrc $end
$var wire 1 ) clk $end
$var wire 32 N instr [31:0] $end
$var wire 1 > jump $end
$var wire 1 = memtoreg $end
$var wire 1 ; pcsrc $end
$var wire 32 O readdata [31:0] $end
$var wire 1 : regdst $end
$var wire 1 9 regwrite $end
$var wire 1 * reset $end
$var wire 1 7 zero $end
$var wire 5 P writereg [4:0] $end
$var wire 32 Q writedata [31:0] $end
$var wire 32 R srcb [31:0] $end
$var wire 32 S srca [31:0] $end
$var wire 32 T signimmsh [31:0] $end
$var wire 32 U signimm [31:0] $end
$var wire 32 V result [31:0] $end
$var wire 32 W pcplus4 [31:0] $end
$var wire 32 X pcnextbr [31:0] $end
$var wire 32 Y pcnext [31:0] $end
$var wire 32 Z pcbranch [31:0] $end
$var wire 32 [ pc [31:0] $end
$var wire 32 \ aluout [31:0] $end
$scope module alu $end
$var wire 4 ] op [3:0] $end
$var wire 32 ^ result [31:0] $end
$var wire 32 _ logicout [31:0] $end
$var wire 1 7 cero $end
$var wire 32 ` b [31:0] $end
$var wire 32 a arithout [31:0] $end
$var wire 32 b a [31:0] $end
$scope module a_block $end
$var wire 1 c op1 $end
$var wire 1 d op3 $end
$var wire 32 e b [31:0] $end
$var wire 32 f arithout [31:0] $end
$var wire 32 g addout [31:0] $end
$var wire 32 h a [31:0] $end
$scope module first_adder_substractor $end
$var wire 1 c s $end
$var wire 32 i y [31:0] $end
$var wire 32 j con [31:0] $end
$var wire 32 k b [31:0] $end
$var wire 32 l a [31:0] $end
$scope module first_adder $end
$var wire 1 c s $end
$var wire 32 m b [31:0] $end
$var wire 32 n a [31:0] $end
$var reg 32 o y [31:0] $end
$upscope $end
$scope module first_mux $end
$var wire 32 p b [31:0] $end
$var wire 1 c s $end
$var wire 32 q y [31:0] $end
$var wire 32 r a [31:0] $end
$upscope $end
$upscope $end
$scope module first_stl $end
$var wire 32 s a [31:0] $end
$var wire 1 d s $end
$var wire 32 t y [31:0] $end
$var reg 32 u extend [31:0] $end
$scope module first_mux $end
$var wire 32 v a [31:0] $end
$var wire 32 w b [31:0] $end
$var wire 1 d s $end
$var wire 32 x y [31:0] $end
$upscope $end
$upscope $end
$upscope $end
$scope module answer $end
$var wire 32 y a [31:0] $end
$var wire 1 z s $end
$var wire 32 { y [31:0] $end
$var wire 32 | b [31:0] $end
$upscope $end
$scope module l_block $end
$var wire 4 } op [3:0] $end
$var wire 32 ~ b [31:0] $end
$var wire 32 !" a [31:0] $end
$var reg 32 "" logicout [31:0] $end
$upscope $end
$scope module z_block $end
$var wire 32 #" a [31:0] $end
$var reg 1 7 y $end
$upscope $end
$upscope $end
$scope module immsh $end
$var wire 32 $" y [31:0] $end
$var wire 32 %" a [31:0] $end
$upscope $end
$scope module pcadd1 $end
$var wire 32 &" b [31:0] $end
$var wire 32 '" y [31:0] $end
$var wire 32 (" a [31:0] $end
$upscope $end
$scope module pcadd2 $end
$var wire 32 )" a [31:0] $end
$var wire 32 *" b [31:0] $end
$var wire 32 +" y [31:0] $end
$upscope $end
$scope module pcbrmux $end
$var wire 32 ," d0 [31:0] $end
$var wire 32 -" d1 [31:0] $end
$var wire 1 ; s $end
$var wire 32 ." y [31:0] $end
$upscope $end
$scope module pcmux $end
$var wire 32 /" d0 [31:0] $end
$var wire 32 0" d1 [31:0] $end
$var wire 1 > s $end
$var wire 32 1" y [31:0] $end
$upscope $end
$scope module pcreg $end
$var wire 1 ) clk $end
$var wire 32 2" d [31:0] $end
$var wire 1 * reset $end
$var reg 32 3" q [31:0] $end
$upscope $end
$scope module resmux $end
$var wire 32 4" d0 [31:0] $end
$var wire 32 5" d1 [31:0] $end
$var wire 1 = s $end
$var wire 32 6" y [31:0] $end
$upscope $end
$scope module rf $end
$var wire 1 ) clk $end
$var wire 5 7" ra1 [4:0] $end
$var wire 5 8" ra2 [4:0] $end
$var wire 32 9" wd3 [31:0] $end
$var wire 1 9 we3 $end
$var wire 5 :" wa3 [4:0] $end
$var wire 32 ;" rd2 [31:0] $end
$var wire 32 <" rd1 [31:0] $end
$upscope $end
$scope module se $end
$var wire 16 =" a [15:0] $end
$var wire 32 >" y [31:0] $end
$upscope $end
$scope module srcbmux $end
$var wire 32 ?" d0 [31:0] $end
$var wire 32 @" d1 [31:0] $end
$var wire 1 ? s $end
$var wire 32 A" y [31:0] $end
$upscope $end
$scope module wrmux $end
$var wire 5 B" d0 [4:0] $end
$var wire 5 C" d1 [4:0] $end
$var wire 1 : s $end
$var wire 5 D" y [4:0] $end
$upscope $end
$upscope $end
$upscope $end
$upscope $end
$upscope $end
$enddefinitions $end
#0
$dumpvars
b10 D"
b0 C"
b10 B"
b101 A"
b101 @"
bx ?"
b101 >"
b101 ="
b0 <"
bx ;"
b10 :"
b101 9"
b10 8"
b0 7"
b101 6"
bx 5"
b101 4"
b0 3"
b100 2"
b100 1"
b10000000000000010100 0"
b100 /"
b100 ."
b11000 -"
b100 ,"
b11000 +"
b10100 *"
b100 )"
b0 ("
b100 '"
b100 &"
b101 %"
b10100 $"
b101 #"
bx ""
b0 !"
b101 ~
b0 }
bx |
b101 {
0z
b101 y
b101 x
b0 w
b101 v
b0 u
b101 t
b101 s
b101 r
b101 q
b11111111111111111111111111111010 p
b101 o
b0 n
b101 m
b0 l
b101 k
b101 j
b101 i
b0 h
b101 g
b101 f
b101 e
0d
0c
b0 b
b101 a
b101 `
bx _
b101 ^
b0 ]
b101 \
b0 [
b11000 Z
b100 Y
b100 X
b100 W
b101 V
b101 U
b10100 T
b0 S
b101 R
bx Q
b10 P
bx O
b100000000000100000000000000101 N
b0 M
b101000000 L
b0 K
b1000 J
b0 I
b0 H
b101 G
b0 F
b0 E
0D
b1000 C
b101 B
b0 A
b101 @
1?
0>
0=
b0 <
0;
0:
19
bx 8
07
bx 6
b100000000000100000000000000101 5
b100000000000100000000000000101 4
b0 3
b101 2
bx 1
bx 0
b101 /
b100000000000100000000000000101 .
b0 -
bx ,
bx +
1*
1)
b101 (
0'
bx &
bx %
z$
z#
bz "
z!
$end
#5
0)
#10
b101 &
b101 +
b101 1
b101 8
b101 Q
b101 ;"
b101 ?"
1)
#15
0)
#20
1)
#22
0*
#25
0)
#30
b1100 V
b1100 6"
b1100 9"
b1100 (
b1100 /
b1100 2
b1100 @
b1100 \
b1100 ^
b1100 {
b1100 #"
b1100 4"
b1100 a
b1100 f
b1100 t
b1100 x
b1100 y
b1100 g
b1100 i
b1100 o
b1100 s
b1100 v
b1100 j
b1100 m
b1100 q
b11111111111111111111111111110011 p
bx &
bx +
bx 1
bx 8
bx Q
bx ;"
bx ?"
b11 P
b11 :"
b11 D"
b1100 R
b1100 `
b1100 e
b1100 k
b1100 r
b1100 ~
b1100 A"
b110000 T
b110000 $"
b110000 *"
b1000 Y
b1000 1"
b1000 2"
b1100 B
b1100 G
b11000000000000110000 0"
b11 8"
b11 B"
b1100 U
b1100 %"
b1100 >"
b1100 @"
b1100 ="
b1000 X
b1000 ."
b1000 /"
b100000000000110000000000001100 .
b100000000000110000000000001100 4
b100000000000110000000000001100 5
b100000000000110000000000001100 N
b1 3
b111000 Z
b111000 +"
b111000 -"
b1000 W
b1000 '"
b1000 )"
b1000 ,"
b100 -
b100 <
b100 [
b100 ("
b100 3"
1)
#35
0)
#40
b11 V
b11 6"
b11 9"
b11 (
b11 /
b11 2
b11 @
b11 \
b11 ^
b11 {
b11 #"
b11 4"
b11 a
b11 f
b11 t
b11 x
b11 y
b11 g
b11 i
b11 o
b11 s
b11 v
b11111111111111111111111111110111 j
b11111111111111111111111111110111 m
b11111111111111111111111111110111 q
b1000 p
b1100 S
b1100 b
b1100 h
b1100 l
b1100 n
b1100 !"
b1100 <"
b111 P
b111 :"
b111 D"
b11111111111111111111111111110111 R
b11111111111111111111111111110111 `
b11111111111111111111111111110111 e
b11111111111111111111111111110111 k
b11111111111111111111111111110111 r
b11111111111111111111111111110111 ~
b11111111111111111111111111110111 A"
b11111111111111111111111111011100 T
b11111111111111111111111111011100 $"
b11111111111111111111111111011100 *"
b1100 Y
b1100 1"
b1100 2"
b110111 B
b110111 G
b1100111111111111111011100 0"
b11 7"
b111 8"
b111 B"
b11111 C"
b11111111111111111111111111110111 U
b11111111111111111111111111110111 %"
b11111111111111111111111111110111 >"
b11111111111111111111111111110111 @"
b1111111111110111 ="
bx &
bx +
bx 1
bx 8
bx Q
bx ;"
bx ?"
b1100 X
b1100 ."
b1100 /"
b100000011001111111111111110111 .
b100000011001111111111111110111 4
b100000011001111111111111110111 5
b100000011001111111111111110111 N
b10 3
b11111111111111111111111111101000 Z
b11111111111111111111111111101000 +"
b11111111111111111111111111101000 -"
b1100 W
b1100 '"
b1100 )"
b1100 ,"
b1000 -
b1000 <
b1000 [
b1000 ("
b1000 3"
1)
#45
0)
#50
1z
b111 _
b111 |
b111 ""
b101 A
b101 F
b101 I
b101 M
b101 ]
b101 }
b111 V
b111 6"
b111 9"
b111 (
b111 /
b111 2
b111 @
b111 \
b111 ^
b111 {
b111 #"
b111 4"
b1000 a
b1000 f
b1000 t
b1000 x
b1000 y
1:
0?
b10 E
b10 H
b10 K
b1000 g
b1000 i
b1000 o
b1000 s
b1000 v
b110000010 L
b101 j
b101 m
b101 q
b11111111111111111111111111111010 p
b11 S
b11 b
b11 h
b11 l
b11 n
b11 !"
b11 <"
b100 P
b100 :"
b100 D"
b101 R
b101 `
b101 e
b101 k
b101 r
b101 ~
b101 A"
b1000000010010100 T
b1000000010010100 $"
b1000000010010100 *"
b10000 Y
b10000 1"
b10000 2"
b0 C
b0 J
b100101 B
b100101 G
b11100010001000000010010100 0"
b111 7"
b10 8"
b10 B"
b100 C"
b10000000100101 U
b10000000100101 %"
b10000000100101 >"
b10000000100101 @"
b10000000100101 ="
b101 &
b101 +
b101 1
b101 8
b101 Q
b101 ;"
b101 ?"
b10000 X
b10000 ."
b10000 /"
b111000100010000000100101 .
b111000100010000000100101 4
b111000100010000000100101 5
b111000100010000000100101 N
b11 3
b1000000010100100 Z
b1000000010100100 +"
b1000000010100100 -"
b10000 W
b10000 '"
b10000 )"
b10000 ,"
b1100 -
b1100 <
b1100 [
b1100 ("
b1100 3"
1)
#55
0)
#60
b100 V
b100 6"
b100 9"
b100 (
b100 /
b100 2
b100 @
b100 \
b100 ^
b100 {
b100 #"
b100 4"
b10011 a
b10011 f
b10011 t
b10011 x
b10011 y
b100 _
b100 |
b100 ""
b10011 g
b10011 i
b10011 o
b10011 s
b10011 v
b100 A
b100 F
b100 I
b100 M
b100 ]
b100 }
b111 j
b111 m
b111 q
b11111111111111111111111111111000 p
b111 R
b111 `
b111 e
b111 k
b111 r
b111 ~
b111 A"
b1100 S
b1100 b
b1100 h
b1100 l
b1100 n
b1100 !"
b1100 <"
b111 &
b111 +
b111 1
b111 8
b111 Q
b111 ;"
b111 ?"
b101 P
b101 :"
b101 D"
b1010000010010000 T
b1010000010010000 $"
b1010000010010000 *"
b10100 Y
b10100 1"
b10100 2"
b100100 B
b100100 G
b1100100001010000010010000 0"
b11 7"
b100 8"
b100 B"
b101 C"
b10100000100100 U
b10100000100100 %"
b10100000100100 >"
b10100000100100 @"
b10100000100100 ="
b10100 X
b10100 ."
b10100 /"
b11001000010100000100100 .
b11001000010100000100100 4
b11001000010100000100100 5
b11001000010100000100100 N
b100 3
b1010000010100100 Z
b1010000010100100 +"
b1010000010100100 -"
b10100 W
b10100 '"
b10100 )"
b10100 ,"
b10000 -
b10000 <
b10000 [
b10000 ("
b10000 3"
1)
#65
0)
#70
b1011 V
b1011 6"
b1011 9"
b1011 (
b1011 /
b1011 2
b1011 @
b1011 \
b1011 ^
b1011 {
b1011 #"
b1011 4"
b1011 a
b1011 f
b1011 t
b1011 x
b1011 y
0z
bx _
bx |
bx ""
b1011 g
b1011 i
b1011 o
b1011 s
b1011 v
b0 A
b0 F
b0 I
b0 M
b0 ]
b0 }
b100 S
b100 b
b100 h
b100 l
b100 n
b100 !"
b100 <"
b1010000010000000 T
b1010000010000000 $"
b1010000010000000 *"
b11000 Y
b11000 1"
b11000 2"
b100000 B
b100000 G
b10100100001010000010000000 0"
b101 7"
b10100000100000 U
b10100000100000 %"
b10100000100000 >"
b10100000100000 @"
b10100000100000 ="
b11000 X
b11000 ."
b11000 /"
b101001000010100000100000 .
b101001000010100000100000 4
b101001000010100000100000 5
b101001000010100000100000 N
b101 3
b1010000010011000 Z
b1010000010011000 +"
b1010000010011000 -"
b11000 W
b11000 '"
b11000 )"
b11000 ,"
b10100 -
b10100 <
b10100 [
b10100 ("
b10100 3"
1)
#75
0)
#80
b1000 V
b1000 6"
b1000 9"
b1000 (
b1000 /
b1000 2
b1000 @
b1000 \
b1000 ^
b1000 {
b1000 #"
b1000 4"
09
0:
1D
b1 E
b1 H
b1 K
1c
0d
0z
b1000 a
b1000 f
b1000 t
b1000 x
b1000 y
b100001 L
b10 A
b10 F
b10 I
b10 M
b10 ]
b10 }
b1000 g
b1000 i
b1000 o
b1000 s
b1000 v
b11111111111111111111111111111100 j
b11111111111111111111111111111100 m
b11111111111111111111111111111100 q
b11111111111111111111111111111100 p
b11 R
b11 `
b11 e
b11 k
b11 r
b11 ~
b11 A"
b11 &
b11 +
b11 1
b11 8
b11 Q
b11 ;"
b11 ?"
b111 P
b111 :"
b111 D"
b101000 T
b101000 $"
b101000 *"
b11100 Y
b11100 1"
b11100 2"
b100 C
b100 J
b1010 B
b1010 G
b10100111000000000000101000 0"
b111 8"
b111 B"
b0 C"
b1010 U
b1010 %"
b1010 >"
b1010 @"
b1010 ="
b1011 S
b1011 b
b1011 h
b1011 l
b1011 n
b1011 !"
b1011 <"
b11100 X
b11100 ."
b11100 /"
b10000101001110000000000001010 .
b10000101001110000000000001010 4
b10000101001110000000000001010 5
b10000101001110000000000001010 N
b110 3
b1000100 Z
b1000100 +"
b1000100 -"
b11100 W
b11100 '"
b11100 )"
b11100 ,"
b11000 -
b11000 <
b11000 [
b11000 ("
b11000 3"
1)
#85
0)
#90
17
1d
b1010 A
b1010 F
b1010 I
b1010 M
b1010 ]
b1010 }
b0 V
b0 6"
b0 9"
b0 (
b0 /
b0 2
b0 @
b0 \
b0 ^
b0 {
b0 #"
b0 4"
b0 a
b0 f
b0 t
b0 x
b0 y
19
1:
0D
b10 E
b10 H
b10 K
b101 g
b101 i
b101 o
b101 s
b101 v
b110000010 L
b11111111111111111111111111111000 j
b11111111111111111111111111111000 m
b11111111111111111111111111111000 q
b11111111111111111111111111111000 p
b111 R
b111 `
b111 e
b111 k
b111 r
b111 ~
b111 A"
b1100 S
b1100 b
b1100 h
b1100 l
b1100 n
b1100 !"
b1100 <"
b111 &
b111 +
b111 1
b111 8
b111 Q
b111 ;"
b111 ?"
b100 P
b100 :"
b100 D"
b1000000010101000 T
b1000000010101000 $"
b1000000010101000 *"
b100000 Y
b100000 1"
b100000 2"
b0 C
b0 J
b101010 B
b101010 G
b1100100001000000010101000 0"
b11 7"
b100 8"
b100 B"
b100 C"
b10000000101010 U
b10000000101010 %"
b10000000101010 >"
b10000000101010 @"
b10000000101010 ="
b100000 X
b100000 ."
b100000 /"
b11001000010000000101010 .
b11001000010000000101010 4
b11001000010000000101010 5
b11001000010000000101010 N
b111 3
b1000000011001000 Z
b1000000011001000 +"
b1000000011001000 -"
b100000 W
b100000 '"
b100000 )"
b100000 ,"
b11100 -
b11100 <
b11100 [
b11100 ("
b11100 3"
1)
#95
0)
#100
b0 V
b0 6"
b0 9"
17
1;
b0 (
b0 /
b0 2
b0 @
b0 \
b0 ^
b0 {
b0 #"
b0 4"
09
0:
1D
b1 E
b1 H
b1 K
1c
0d
0z
b0 g
b0 i
b0 o
b0 s
b0 v
b100001 L
b10 A
b10 F
b10 I
b10 M
b10 ]
b10 }
b11111111111111111111111111111111 j
b11111111111111111111111111111111 m
b11111111111111111111111111111111 q
b11111111111111111111111111111111 p
b0 S
b0 b
b0 h
b0 l
b0 n
b0 !"
b0 <"
b0 P
b0 :"
b0 D"
b100 T
b100 $"
b100 *"
b0 R
b0 `
b0 e
b0 k
b0 r
b0 ~
b0 A"
b101000 Y
b101000 1"
b101000 2"
b100 C
b100 J
b1 B
b1 G
b10000000000000000000000100 0"
b100 7"
b0 8"
b0 B"
b0 C"
b1 U
b1 %"
b1 >"
b1 @"
b1 ="
b0 &
b0 +
b0 1
b0 8
b0 Q
b0 ;"
b0 ?"
b101000 X
b101000 ."
b101000 /"
b10000100000000000000000000001 .
b10000100000000000000000000001 4
b10000100000000000000000000001 5
b10000100000000000000000000001 N
b1000 3
b101000 Z
b101000 +"
b101000 -"
b100100 W
b100100 '"
b100100 )"
b100100 ,"
b100000 -
b100000 <
b100000 [
b100000 ("
b100000 3"
1)
#105
0)
