Lab_05/cero.v
module cero(a, y);
	input [31:0] a;
	output reg y;
	always @(*)begin
	if(a==32'b0)
	begin
		y = 1;
	end	
	else
	begin
		y = 0;
	end
	end
endmodule

Lab_05/mux2x1.v
module mux2x1 (a, b, s, y);
	input [31:0] a, b;
	input s;
	output [31:0]y;
	assign y = s? b : a;
endmodule

Lab_05/l_part.v
module l_part(a, b, op, logicout);
	input [31:0] a, b;
	input [1:0] op;
	output reg[31:0] logicout;

	always @ (op) begin
		case(op)
		2'b00	:	logicout = a & b;	
		2'b01	:	logicout = a | b;
		2'b10	:	logicout = a ^ b;
		2'b11	:	logicout = a ~| b;
		default :	logicout = 32'b0;
		endcase
	end
endmodule

Lab_05/stl.v
module stl(a, s, y);
	input [31:0] a;
	input s;
	reg [31:0] extend;
	output [31:0] y;
	always @(*)begin
		extend = {32{a[31]}};	
	end

	mux2x1 first_mux(a, extend, s, y);
endmodule

Lab_05/adder.v
module adder(a, b, s, y);
	input [31:0] a, b;
	input s;
	output reg[31:0] y;
	always @(*)begin
	case(s)
	1'b1:	y <= a + b + 1;
	1'b0:	y <= a + b;
	endcase
end	
endmodule

Lab_05/adder_substractor.v
module adder_substractor(a, b, s, y);
	input [31:0] a, b;
	input s;
	wire [31:0] con;
	output [31:0] y;
	mux2x1 first_mux(b, ~b, s, con);
	adder  first_adder(a, con, s, y);
endmodule

Lab_05/a_part.v
module a_part(a, b, op1, op3, arithout);
	input [31:0] a, b;
	input op1, op3;
	wire [31:0] addout;
	output [31:0] arithout;
	adder_substractor first_adder_substractor(a, b, op1, addout);
	stl first_stl(addout, op3, arithout);
endmodule

Lab_05/alu.v
module alu(a, b, op, result, cero);
	input [31:0] a, b;
	input [3:0] op;
	output [31:0] result;
	output cero;
	wire [31:0]arithout, logicout;

		a_part a_block(a, b, op[1], op[3], arithout);
		l_part l_block(a, b, op[1:0], logicout);
		mux2x1 answer(arithout, logicout, op[2], result);
		cero z_block(result, cero);
endmodule

Lab_05/alu_tb.v
`timescale 1ns/1ns
module alu_tb;
	reg [31:0] a, b;
	reg [3:0] op;
	wire [31:0] result;
	wire cero;

	alu g(a, b, op, result, cero);
	initial begin
		$display("time\t\t\tA\t\t\t\t\tB\t\t\topcode\t\t\tresult\t\t\tZero");
		a = 32'b100;
		b = 32'b101;
		op = 4'b0;
		#10 $finish;
	end
	initial begin
		$monitor("%2d\t%b\t%b\t%b\t%b\t%b", $time, a, b, op, result, cero);
	end
	
	initial begin
	#1 op = 4'b0010;
	#1 op = 4'b0010;	
	#1 op = 4'b0100;	
	#1 op = 4'b0101;	
	#1 op = 4'b0110;	
	#1 op = 4'b0111;	
	#1 op = 4'b1010;
	#1 op = 4'b1111;		
	end

	initial begin
		$dumpfile("alu.vcd");	
		$dumpvars;
	end	

endmodule

Lab_05/alu.vcd
$date
	Sat Jun 13 21:49:25 2020
$end
$version
	Icarus Verilog
$end
$timescale
	1ns
$end
$scope module alu_tb $end
$var wire 32 ! result [31:0] $end
$var wire 1 " cero $end
$var reg 32 # a [31:0] $end
$var reg 32 $ b [31:0] $end
$var reg 4 % op [3:0] $end
$scope module g $end
$var wire 32 & a [31:0] $end
$var wire 32 ' b [31:0] $end
$var wire 4 ( op [3:0] $end
$var wire 32 ) result [31:0] $end
$var wire 32 * logicout [31:0] $end
$var wire 1 " cero $end
$var wire 32 + arithout [31:0] $end
$scope module a_block $end
$var wire 32 , a [31:0] $end
$var wire 32 - b [31:0] $end
$var wire 1 . op1 $end
$var wire 1 / op3 $end
$var wire 32 0 arithout [31:0] $end
$var wire 32 1 addout [31:0] $end
$scope module first_adder_substractor $end
$var wire 32 2 a [31:0] $end
$var wire 32 3 b [31:0] $end
$var wire 1 . s $end
$var wire 32 4 y [31:0] $end
$var wire 32 5 con [31:0] $end
$scope module first_adder $end
$var wire 32 6 a [31:0] $end
$var wire 1 . s $end
$var wire 32 7 b [31:0] $end
$var reg 32 8 y [31:0] $end
$upscope $end
$scope module first_mux $end
$var wire 32 9 a [31:0] $end
$var wire 32 : b [31:0] $end
$var wire 1 . s $end
$var wire 32 ; y [31:0] $end
$upscope $end
$upscope $end
$scope module first_stl $end
$var wire 32 < a [31:0] $end
$var wire 1 / s $end
$var wire 32 = y [31:0] $end
$var reg 32 > extend [31:0] $end
$scope module first_mux $end
$var wire 32 ? a [31:0] $end
$var wire 32 @ b [31:0] $end
$var wire 1 / s $end
$var wire 32 A y [31:0] $end
$upscope $end
$upscope $end
$upscope $end
$scope module answer $end
$var wire 32 B a [31:0] $end
$var wire 1 C s $end
$var wire 32 D y [31:0] $end
$var wire 32 E b [31:0] $end
$upscope $end
$scope module l_block $end
$var wire 32 F a [31:0] $end
$var wire 32 G b [31:0] $end
$var wire 2 H op [1:0] $end
$var reg 32 I logicout [31:0] $end
$upscope $end
$scope module z_block $end
$var wire 32 J a [31:0] $end
$var reg 1 " y $end
$upscope $end
$upscope $end
$upscope $end
$enddefinitions $end
#0
$dumpvars
b1001 J
b100 I
b0 H
b101 G
b100 F
b100 E
b1001 D
0C
b1001 B
b1001 A
b0 @
b1001 ?
b0 >
b1001 =
b1001 <
b101 ;
b11111111111111111111111111111010 :
b101 9
b1001 8
b101 7
b100 6
b101 5
b1001 4
b101 3
b100 2
b1001 1
b1001 0
0/
0.
b101 -
b100 ,
b1001 +
b100 *
b1001 )
b0 (
b101 '
b100 &
b0 %
b101 $
b100 #
0"
b1001 !
$end
#1
b11111111111111111111111111111111 !
b11111111111111111111111111111111 )
b11111111111111111111111111111111 D
b11111111111111111111111111111111 J
b11111111111111111111111111111111 >
b11111111111111111111111111111111 @
b11111111111111111111111111111111 +
b11111111111111111111111111111111 0
b11111111111111111111111111111111 =
b11111111111111111111111111111111 A
b11111111111111111111111111111111 B
b11111111111111111111111111111111 1
b11111111111111111111111111111111 4
b11111111111111111111111111111111 8
b11111111111111111111111111111111 <
b11111111111111111111111111111111 ?
b11111111111111111111111111111010 5
b11111111111111111111111111111010 7
b11111111111111111111111111111010 ;
b1 *
b1 E
b1 I
1.
b10 H
b10 %
b10 (
#3
b0 >
b0 @
b1001 +
b1001 0
b1001 =
b1001 A
b1001 B
b1001 1
b1001 4
b1001 8
b1001 <
b1001 ?
b101 5
b101 7
b101 ;
b100 *
b100 E
b100 I
b100 !
b100 )
b100 D
b100 J
0.
b0 H
1C
b100 %
b100 (
#4
b101 !
b101 )
b101 D
b101 J
b101 *
b101 E
b101 I
b1 H
b101 %
b101 (
#5
b11111111111111111111111111111111 >
b11111111111111111111111111111111 @
b11111111111111111111111111111111 +
b11111111111111111111111111111111 0
b11111111111111111111111111111111 =
b11111111111111111111111111111111 A
b11111111111111111111111111111111 B
b11111111111111111111111111111111 1
b11111111111111111111111111111111 4
b11111111111111111111111111111111 8
b11111111111111111111111111111111 <
b11111111111111111111111111111111 ?
b1 !
b1 )
b1 D
b1 J
b11111111111111111111111111111010 5
b11111111111111111111111111111010 7
b11111111111111111111111111111010 ;
b1 *
b1 E
b1 I
1.
b10 H
b110 %
b110 (
#6
b11111111111111111111111111111010 !
b11111111111111111111111111111010 )
b11111111111111111111111111111010 D
b11111111111111111111111111111010 J
b11111111111111111111111111111010 *
b11111111111111111111111111111010 E
b11111111111111111111111111111010 I
b11 H
b111 %
b111 (
#7
b1 *
b1 E
b1 I
b11111111111111111111111111111111 !
b11111111111111111111111111111111 )
b11111111111111111111111111111111 D
b11111111111111111111111111111111 J
1/
b10 H
0C
b1010 %
b1010 (
#8
b11111111111111111111111111111010 *
b11111111111111111111111111111010 E
b11111111111111111111111111111010 I
b11111111111111111111111111111010 !
b11111111111111111111111111111010 )
b11111111111111111111111111111010 D
b11111111111111111111111111111010 J
b11 H
1C
b1111 %
b1111 (
