Lab_02/demux16_1x8.v
module demux16_1x8(D0, s, y0, y1, y2, y3, y4, y5, y6, y7); 
	input [15:0] D0; 
	input [2:0]s; 
	output [15:0]  y0, y1, y2, y3, y4, y5, y6, y7; 
	assign y0 = (s == 3'b000) ? D0 : 16'b0; 
	assign y1 = (s == 3'b001) ? D0 : 16'b0; 
	assign y2 = (s == 3'b010) ? D0 : 16'b0; 
	assign y3 = (s == 3'b011) ? D0 : 16'b0; 
	assign y4 = (s == 3'b100) ? D0 : 16'b0; 
	assign y5 = (s == 3'b101) ? D0 : 16'b0; 
	assign y6 = (s == 3'b110) ? D0 : 16'b0; 
	assign y7 = (s == 3'b111) ? D0 : 16'b0; 
endmodule

Lab_02/demux16_1x8_tb.v
`timescale 1ns/1ns
module demux16_1x8_tb;
	reg [15:0]D0;
	reg [2:0]s;
	wire [15:0]  y0, y1, y2, y3, y4, y5, y6, y7;
	demux16_1x8 g(D0, s, y0, y1, y2, y3, y4, y5, y6, y7);
	initial begin
	$display("time\t\tD0\t\ts\t\ty0\t\t\ty1\t\t\ty2\t\t\ty3\t\t\ty4\t\t\ty5\t\t\ty6\t\t\ty7");
		D0 = 16'b01;
		s = 3'b000;
		#8 $finish;
	end
	initial begin
		$monitor("%2d:\t%b\t%b\t%b\t%b\t%b\t%b\t%b\t%b\t%b\t%b",$time,D0, s, y0, y1, y2, y3, y4, y5, y6, y7);
	end
	always #1 s[0] = !s[0];
	always #2 s[1] = !s[1];
	always #4 s[2] = !s[2];	
	initial begin
		$dumpfile("demux16_1x8.vcd");	
		$dumpvars;
	end	
endmodule

Lab_02/demux1x8/demux16_1x8.vcd
$date
	Mon May  4 00:23:56 2020
$end
$version
	Icarus Verilog
$end
$timescale
	1ns
$end
$scope module demux16_1x8_tb $end
$var wire 16 ! y7 [15:0] $end
$var wire 16 " y6 [15:0] $end
$var wire 16 # y5 [15:0] $end
$var wire 16 $ y4 [15:0] $end
$var wire 16 % y3 [15:0] $end
$var wire 16 & y2 [15:0] $end
$var wire 16 ' y1 [15:0] $end
$var wire 16 ( y0 [15:0] $end
$var reg 16 ) D0 [15:0] $end
$var reg 3 * s [2:0] $end
$scope module g $end
$var wire 16 + D0 [15:0] $end
$var wire 3 , s [2:0] $end
$var wire 16 - y7 [15:0] $end
$var wire 16 . y6 [15:0] $end
$var wire 16 / y5 [15:0] $end
$var wire 16 0 y4 [15:0] $end
$var wire 16 1 y3 [15:0] $end
$var wire 16 2 y2 [15:0] $end
$var wire 16 3 y1 [15:0] $end
$var wire 16 4 y0 [15:0] $end
$upscope $end
$upscope $end
$enddefinitions $end
#0
$dumpvars
b1 4
b0 3
b0 2
b0 1
b0 0
b0 /
b0 .
b0 -
b0 ,
b1 +
b0 *
b1 )
b1 (
b0 '
b0 &
b0 %
b0 $
b0 #
b0 "
b0 !
$end
#1
b0 (
b0 4
b1 '
b1 3
b1 *
b1 ,
#2
b1 &
b1 2
b0 '
b0 3
b10 *
b10 ,
#3
b0 &
b0 2
b1 %
b1 1
b11 *
b11 ,
#4
b1 $
b1 0
b0 %
b0 1
b100 *
b100 ,
#5
b0 $
b0 0
b1 #
b1 /
b101 *
b101 ,
#6
b1 "
b1 .
b0 #
b0 /
b110 *
b110 ,
#7
b0 "
b0 .
b1 !
b1 -
b111 *
b111 ,
#8
b1 (
b1 4
b0 !
b0 -
b0 *
b0 ,
